{
"meta":{"test_sets":[],"test_metrics":[],"learn_metrics":[{"best_value":"Min","name":"RMSE"}],"launch_mode":"Train","parameters":"","iteration_count":1000,"learn_sets":["learn"],"name":"experiment"},
"iterations":[
{"learn":[14.61268541],"iteration":0,"passed_time":0.08657125302,"remaining_time":86.48468177},
{"learn":[14.23196558],"iteration":1,"passed_time":0.08721891357,"remaining_time":43.52223787},
{"learn":[13.86674177],"iteration":2,"passed_time":0.08777551682,"remaining_time":29.17073009},
{"learn":[13.49946468],"iteration":3,"passed_time":0.08833084567,"remaining_time":21.99438057},
{"learn":[13.16661202],"iteration":4,"passed_time":0.08889874311,"remaining_time":17.69084988},
{"learn":[12.85632158],"iteration":5,"passed_time":0.08945688556,"remaining_time":14.82002404},
{"learn":[12.56784336],"iteration":6,"passed_time":0.09003784372,"remaining_time":12.77251126},
{"learn":[12.31617801],"iteration":7,"passed_time":0.09055633673,"remaining_time":11.22898575},
{"learn":[12.01509946],"iteration":8,"passed_time":0.0911452332,"remaining_time":10.0361029},
{"learn":[11.71512571],"iteration":9,"passed_time":0.09168316536,"remaining_time":9.07663337},
{"learn":[11.43264457],"iteration":10,"passed_time":0.09224365452,"remaining_time":8.29354312},
{"learn":[11.17973129],"iteration":11,"passed_time":0.09273360397,"remaining_time":7.635066727},
{"learn":[10.93746433],"iteration":12,"passed_time":0.09330512288,"remaining_time":7.084012022},
{"learn":[10.69387075],"iteration":13,"passed_time":0.09390061286,"remaining_time":6.61328602},
{"learn":[10.4615922],"iteration":14,"passed_time":0.09447106212,"remaining_time":6.203599746},
{"learn":[10.2299235],"iteration":15,"passed_time":0.09496403604,"remaining_time":5.840288216},
{"learn":[10.01419731],"iteration":16,"passed_time":0.09547272087,"remaining_time":5.520569683},
{"learn":[9.795856918],"iteration":17,"passed_time":0.09593985002,"remaining_time":5.234051818},
{"learn":[9.60040151],"iteration":18,"passed_time":0.09642410722,"remaining_time":4.978528904},
{"learn":[9.418664989],"iteration":19,"passed_time":0.09694557455,"remaining_time":4.750333153},
{"learn":[9.249278645],"iteration":20,"passed_time":0.0974355351,"remaining_time":4.542351851},
{"learn":[9.090113396],"iteration":21,"passed_time":0.09791459641,"remaining_time":4.352748877},
{"learn":[8.909548708],"iteration":22,"passed_time":0.09843137148,"remaining_time":4.181193475},
{"learn":[8.740140208],"iteration":23,"passed_time":0.0989702577,"remaining_time":4.02479048},
{"learn":[8.59377682],"iteration":24,"passed_time":0.09943330959,"remaining_time":3.877899074},
{"learn":[8.453885414],"iteration":25,"passed_time":0.0998951223,"remaining_time":3.742224966},
{"learn":[8.317732234],"iteration":26,"passed_time":0.1004006346,"remaining_time":3.618141386},
{"learn":[8.180896085],"iteration":27,"passed_time":0.1008956651,"remaining_time":3.502520945},
{"learn":[8.053220863],"iteration":28,"passed_time":0.1014027437,"remaining_time":3.395243592},
{"learn":[7.924234474],"iteration":29,"passed_time":0.1019602735,"remaining_time":3.29671551},
{"learn":[7.818879511],"iteration":30,"passed_time":0.1024267237,"remaining_time":3.201661139},
{"learn":[7.719346395],"iteration":31,"passed_time":0.102881026,"remaining_time":3.112151036},
{"learn":[7.624163594],"iteration":32,"passed_time":0.1033683616,"remaining_time":3.029006233},
{"learn":[7.524952543],"iteration":33,"passed_time":0.1038134301,"remaining_time":2.94952275},
{"learn":[7.424464745],"iteration":34,"passed_time":0.1043423138,"remaining_time":2.876866651},
{"learn":[7.327482321],"iteration":35,"passed_time":0.1048146936,"remaining_time":2.806704572},
{"learn":[7.238666841],"iteration":36,"passed_time":0.1053027812,"remaining_time":2.740718332},
{"learn":[7.158842395],"iteration":37,"passed_time":0.1058252424,"remaining_time":2.679049557},
{"learn":[7.074348246],"iteration":38,"passed_time":0.1063169385,"remaining_time":2.619758407},
{"learn":[6.992269093],"iteration":39,"passed_time":0.1067939141,"remaining_time":2.563053937},
{"learn":[6.925219745],"iteration":40,"passed_time":0.1073042862,"remaining_time":2.509873426},
{"learn":[6.86013671],"iteration":41,"passed_time":0.1077976597,"remaining_time":2.458813285},
{"learn":[6.786739622],"iteration":42,"passed_time":0.1083483315,"remaining_time":2.411380307},
{"learn":[6.73057926],"iteration":43,"passed_time":0.108892993,"remaining_time":2.365947757},
{"learn":[6.666356486],"iteration":44,"passed_time":0.1094616994,"remaining_time":2.32302051},
{"learn":[6.606182832],"iteration":45,"passed_time":0.1099718818,"remaining_time":2.2807212},
{"learn":[6.547854615],"iteration":46,"passed_time":0.1105185456,"remaining_time":2.240939871},
{"learn":[6.49240675],"iteration":47,"passed_time":0.1110160001,"remaining_time":2.201817336},
{"learn":[6.431317261],"iteration":48,"passed_time":0.1115313783,"remaining_time":2.1646192},
{"learn":[6.377586395],"iteration":49,"passed_time":0.1119613452,"remaining_time":2.127265559},
{"learn":[6.327558015],"iteration":50,"passed_time":0.1125001113,"remaining_time":2.093384423},
{"learn":[6.282040317],"iteration":51,"passed_time":0.1130219307,"remaining_time":2.060476736},
{"learn":[6.237655841],"iteration":52,"passed_time":0.1136747466,"remaining_time":2.031131792},
{"learn":[6.192792003],"iteration":53,"passed_time":0.1141842928,"remaining_time":2.000339649},
{"learn":[6.150579347],"iteration":54,"passed_time":0.1146960194,"remaining_time":1.970686151},
{"learn":[6.115693845],"iteration":55,"passed_time":0.1153129439,"remaining_time":1.943846768},
{"learn":[6.078780782],"iteration":56,"passed_time":0.115928806,"remaining_time":1.917909896},
{"learn":[6.045146957],"iteration":57,"passed_time":0.116402353,"remaining_time":1.890534768},
{"learn":[6.008080327],"iteration":58,"passed_time":0.1169462947,"remaining_time":1.865194294},
{"learn":[5.977575734],"iteration":59,"passed_time":0.1174947174,"remaining_time":1.840750573},
{"learn":[5.948036502],"iteration":60,"passed_time":0.1179576285,"remaining_time":1.815773986},
{"learn":[5.914888282],"iteration":61,"passed_time":0.1184896165,"remaining_time":1.792633231},
{"learn":[5.884957796],"iteration":62,"passed_time":0.1189881648,"remaining_time":1.769712864},
{"learn":[5.849539885],"iteration":63,"passed_time":0.1195195693,"remaining_time":1.747973701},
{"learn":[5.821387627],"iteration":64,"passed_time":0.1200110434,"remaining_time":1.726312702},
{"learn":[5.797012279],"iteration":65,"passed_time":0.1204971024,"remaining_time":1.70521657},
{"learn":[5.768685095],"iteration":66,"passed_time":0.1210673718,"remaining_time":1.685908326},
{"learn":[5.755484587],"iteration":67,"passed_time":0.1214073108,"remaining_time":1.663994318},
{"learn":[5.731887055],"iteration":68,"passed_time":0.1219631475,"remaining_time":1.6456187},
{"learn":[5.707148487],"iteration":69,"passed_time":0.1224363145,"remaining_time":1.626653892},
{"learn":[5.685365039],"iteration":70,"passed_time":0.1229719049,"remaining_time":1.609026756},
{"learn":[5.663541834],"iteration":71,"passed_time":0.1234849127,"remaining_time":1.591583319},
{"learn":[5.638108797],"iteration":72,"passed_time":0.1240144695,"remaining_time":1.57481388},
{"learn":[5.619204893],"iteration":73,"passed_time":0.1245013826,"remaining_time":1.557949734},
{"learn":[5.598472793],"iteration":74,"passed_time":0.1250161191,"remaining_time":1.541865468},
{"learn":[5.577007075],"iteration":75,"passed_time":0.1255377816,"remaining_time":1.526275134},
{"learn":[5.562637084],"iteration":76,"passed_time":0.1260720762,"remaining_time":1.511227614},
{"learn":[5.54729991],"iteration":77,"passed_time":0.1265619682,"remaining_time":1.496027368},
{"learn":[5.530737623],"iteration":78,"passed_time":0.1270363154,"remaining_time":1.48101831},
{"learn":[5.513704873],"iteration":79,"passed_time":0.1275250701,"remaining_time":1.466538306},
{"learn":[5.501575529],"iteration":80,"passed_time":0.1280380186,"remaining_time":1.45267826},
{"learn":[5.484080734],"iteration":81,"passed_time":0.1286985435,"remaining_time":1.44079589},
{"learn":[5.472178894],"iteration":82,"passed_time":0.1293781361,"remaining_time":1.429394588},
{"learn":[5.458923342],"iteration":83,"passed_time":0.1299430557,"remaining_time":1.416998084},
{"learn":[5.451382371],"iteration":84,"passed_time":0.1303385813,"remaining_time":1.403056492},
{"learn":[5.441410748],"iteration":85,"passed_time":0.1309280835,"remaining_time":1.391491493},
{"learn":[5.434047468],"iteration":86,"passed_time":0.1312901674,"remaining_time":1.377792216},
{"learn":[5.422107497],"iteration":87,"passed_time":0.1318405457,"remaining_time":1.366347473},
{"learn":[5.40731265],"iteration":88,"passed_time":0.1323588657,"remaining_time":1.3548194},
{"learn":[5.396360181],"iteration":89,"passed_time":0.1328759825,"remaining_time":1.343523823},
{"learn":[5.383793239],"iteration":90,"passed_time":0.1333664509,"remaining_time":1.332198943},
{"learn":[5.369605034],"iteration":91,"passed_time":0.1338022539,"remaining_time":1.320570071},
{"learn":[5.357467333],"iteration":92,"passed_time":0.1342999595,"remaining_time":1.309785626},
{"learn":[5.341109968],"iteration":93,"passed_time":0.1348037067,"remaining_time":1.29927828},
{"learn":[5.330529276],"iteration":94,"passed_time":0.135216642,"remaining_time":1.288116432},
{"learn":[5.319862075],"iteration":95,"passed_time":0.135784371,"remaining_time":1.278636161},
{"learn":[5.313052243],"iteration":96,"passed_time":0.1363357589,"remaining_time":1.269187528},
{"learn":[5.299677207],"iteration":97,"passed_time":0.1368861004,"remaining_time":1.259910843},
{"learn":[5.287546698],"iteration":98,"passed_time":0.1373881975,"remaining_time":1.250371373},
{"learn":[5.279803754],"iteration":99,"passed_time":0.138018198,"remaining_time":1.242163782},
{"learn":[5.272254612],"iteration":100,"passed_time":0.1386100057,"remaining_time":1.233766288},
{"learn":[5.268813888],"iteration":101,"passed_time":0.1389215871,"remaining_time":1.223054757},
{"learn":[5.258113767],"iteration":102,"passed_time":0.1393510626,"remaining_time":1.213571875},
{"learn":[5.251018576],"iteration":103,"passed_time":0.1398594623,"remaining_time":1.20494306},
{"learn":[5.24171237],"iteration":104,"passed_time":0.1403275256,"remaining_time":1.1961251},
{"learn":[5.233984943],"iteration":105,"passed_time":0.1408516998,"remaining_time":1.187937921},
{"learn":[5.226240449],"iteration":106,"passed_time":0.1413209866,"remaining_time":1.179435898},
{"learn":[5.220541644],"iteration":107,"passed_time":0.1417383703,"remaining_time":1.170653948},
{"learn":[5.211712096],"iteration":108,"passed_time":0.142309921,"remaining_time":1.163285685},
{"learn":[5.203388597],"iteration":109,"passed_time":0.1428229211,"remaining_time":1.155567271},
{"learn":[5.196026544],"iteration":110,"passed_time":0.1434755866,"remaining_time":1.149097266},
{"learn":[5.188716772],"iteration":111,"passed_time":0.1440227307,"remaining_time":1.141894508},
{"learn":[5.182163132],"iteration":112,"passed_time":0.1446536429,"remaining_time":1.13546709},
{"learn":[5.17764747],"iteration":113,"passed_time":0.1451968926,"remaining_time":1.12846006},
{"learn":[5.170548056],"iteration":114,"passed_time":0.1456884062,"remaining_time":1.1211673},
{"learn":[5.165901827],"iteration":115,"passed_time":0.1461225716,"remaining_time":1.11355477},
{"learn":[5.160333668],"iteration":116,"passed_time":0.1466676151,"remaining_time":1.106901744},
{"learn":[5.148953243],"iteration":117,"passed_time":0.1472681161,"remaining_time":1.100766766},
{"learn":[5.144729126],"iteration":118,"passed_time":0.1477058119,"remaining_time":1.093519498},
{"learn":[5.139939946],"iteration":119,"passed_time":0.1482190436,"remaining_time":1.086939653},
{"learn":[5.132898872],"iteration":120,"passed_time":0.1487660258,"remaining_time":1.080705262},
{"learn":[5.129073077],"iteration":121,"passed_time":0.1493061328,"remaining_time":1.074514628},
{"learn":[5.127123916],"iteration":122,"passed_time":0.1496451281,"remaining_time":1.06698193},
{"learn":[5.121282057],"iteration":123,"passed_time":0.1502114301,"remaining_time":1.06117107},
{"learn":[5.114489821],"iteration":124,"passed_time":0.1507316812,"remaining_time":1.055121768},
{"learn":[5.107777291],"iteration":125,"passed_time":0.151252762,"remaining_time":1.049165984},
{"learn":[5.103518754],"iteration":126,"passed_time":0.1518478222,"remaining_time":1.043804321},
{"learn":[5.101133351],"iteration":127,"passed_time":0.1521745064,"remaining_time":1.036688825},
{"learn":[5.096462705],"iteration":128,"passed_time":0.1526841794,"remaining_time":1.030914111},
{"learn":[5.08562082],"iteration":129,"passed_time":0.1533159878,"remaining_time":1.026037765},
{"learn":[5.080483682],"iteration":130,"passed_time":0.1538478075,"remaining_time":1.020562937},
{"learn":[5.07437499],"iteration":131,"passed_time":0.1543841117,"remaining_time":1.015192492},
{"learn":[5.070683732],"iteration":132,"passed_time":0.154923283,"remaining_time":1.009913432},
{"learn":[5.06432037],"iteration":133,"passed_time":0.1554541823,"remaining_time":1.004651656},
{"learn":[5.057436484],"iteration":134,"passed_time":0.1559546097,"remaining_time":0.9992647214},
{"learn":[5.053254656],"iteration":135,"passed_time":0.1564890314,"remaining_time":0.994165611},
{"learn":[5.04801663],"iteration":136,"passed_time":0.1570531611,"remaining_time":0.9893202778},
{"learn":[5.045680836],"iteration":137,"passed_time":0.1575176573,"remaining_time":0.9839146421},
{"learn":[5.041857933],"iteration":138,"passed_time":0.158132379,"remaining_time":0.9795106356},
{"learn":[5.035264888],"iteration":139,"passed_time":0.1586236664,"remaining_time":0.9744025222},
{"learn":[5.028771948],"iteration":140,"passed_time":0.1591131692,"remaining_time":0.969349024},
{"learn":[5.024912247],"iteration":141,"passed_time":0.159580435,"remaining_time":0.9642254454},
{"learn":[5.02239068],"iteration":142,"passed_time":0.1600585618,"remaining_time":0.95923208},
{"learn":[5.017110572],"iteration":143,"passed_time":0.1606341557,"remaining_time":0.9548808142},
{"learn":[5.010707886],"iteration":144,"passed_time":0.1611136762,"remaining_time":0.9500151252},
{"learn":[5.004389868],"iteration":145,"passed_time":0.1616226415,"remaining_time":0.9453817526},
{"learn":[4.997628683],"iteration":146,"passed_time":0.1621058777,"remaining_time":0.9406551951},
{"learn":[4.991497851],"iteration":147,"passed_time":0.1626013281,"remaining_time":0.936056294},
{"learn":[4.988345253],"iteration":148,"passed_time":0.1631402128,"remaining_time":0.931760544},
{"learn":[4.98460423],"iteration":149,"passed_time":0.1637835902,"remaining_time":0.9281070109},
{"learn":[4.982441783],"iteration":150,"passed_time":0.1643687377,"remaining_time":0.9241659491},
{"learn":[4.977461771],"iteration":151,"passed_time":0.164973011,"remaining_time":0.9203757456},
{"learn":[4.973601586],"iteration":152,"passed_time":0.1655834469,"remaining_time":0.9166613039},
{"learn":[4.968328804],"iteration":153,"passed_time":0.1662238308,"remaining_time":0.9131516939},
{"learn":[4.9640736],"iteration":154,"passed_time":0.1668132573,"remaining_time":0.909401306},
{"learn":[4.960865882],"iteration":155,"passed_time":0.1673320967,"remaining_time":0.9053095486},
{"learn":[4.957014156],"iteration":156,"passed_time":0.1678011286,"remaining_time":0.9009958688},
{"learn":[4.952244852],"iteration":157,"passed_time":0.1684100367,"remaining_time":0.8974762717},
{"learn":[4.949695675],"iteration":158,"passed_time":0.1689656159,"remaining_time":0.8937112135},
{"learn":[4.946584698],"iteration":159,"passed_time":0.1694635637,"remaining_time":0.8896837095},
{"learn":[4.940192834],"iteration":160,"passed_time":0.1699351567,"remaining_time":0.8855627108},
{"learn":[4.936727994],"iteration":161,"passed_time":0.1704249982,"remaining_time":0.8815811635},
{"learn":[4.932342063],"iteration":162,"passed_time":0.1709451165,"remaining_time":0.8777979296},
{"learn":[4.925830838],"iteration":163,"passed_time":0.171512544,"remaining_time":0.8742956511},
{"learn":[4.922571773],"iteration":164,"passed_time":0.1721375086,"remaining_time":0.8711201194},
{"learn":[4.918395814],"iteration":165,"passed_time":0.1726720696,"remaining_time":0.8675211208},
{"learn":[4.911142452],"iteration":166,"passed_time":0.1732656151,"remaining_time":0.8642530382},
{"learn":[4.908276131],"iteration":167,"passed_time":0.1738877745,"remaining_time":0.8611585025},
{"learn":[4.904584645],"iteration":168,"passed_time":0.1744745845,"remaining_time":0.8579194069},
{"learn":[4.89795517],"iteration":169,"passed_time":0.1749614288,"remaining_time":0.8542234464},
{"learn":[4.895556491],"iteration":170,"passed_time":0.1754889956,"remaining_time":0.8507624405},
{"learn":[4.890591233],"iteration":171,"passed_time":0.1760479857,"remaining_time":0.8474868149},
{"learn":[4.884629277],"iteration":172,"passed_time":0.1765148259,"remaining_time":0.8438020869},
{"learn":[4.880550786],"iteration":173,"passed_time":0.1769845253,"remaining_time":0.8401679188},
{"learn":[4.876384842],"iteration":174,"passed_time":0.1774945101,"remaining_time":0.8367598334},
{"learn":[4.872638238],"iteration":175,"passed_time":0.1780706191,"remaining_time":0.8336942622},
{"learn":[4.869137118],"iteration":176,"passed_time":0.178676884,"remaining_time":0.8307970367},
{"learn":[4.863587157],"iteration":177,"passed_time":0.1792126596,"remaining_time":0.8276000349},
{"learn":[4.858028614],"iteration":178,"passed_time":0.179680408,"remaining_time":0.8241207539},
{"learn":[4.853838176],"iteration":179,"passed_time":0.1801656365,"remaining_time":0.8207545661},
{"learn":[4.853462329],"iteration":180,"passed_time":0.1804126039,"remaining_time":0.8163421138},
{"learn":[4.851573196],"iteration":181,"passed_time":0.1808736627,"remaining_time":0.8129376708},
{"learn":[4.848442087],"iteration":182,"passed_time":0.1812949737,"remaining_time":0.8093879426},
{"learn":[4.845547104],"iteration":183,"passed_time":0.1817578648,"remaining_time":0.806056618},
{"learn":[4.839868817],"iteration":184,"passed_time":0.1822148885,"remaining_time":0.8027304546},
{"learn":[4.836336958],"iteration":185,"passed_time":0.1827087981,"remaining_time":0.7995965679},
{"learn":[4.831124789],"iteration":186,"passed_time":0.1831630716,"remaining_time":0.7963185948},
{"learn":[4.827407333],"iteration":187,"passed_time":0.1835997931,"remaining_time":0.7929948511},
{"learn":[4.824088918],"iteration":188,"passed_time":0.1840206487,"remaining_time":0.7896335772},
{"learn":[4.820934539],"iteration":189,"passed_time":0.1845632674,"remaining_time":0.7868223504},
{"learn":[4.816975227],"iteration":190,"passed_time":0.1850567457,"remaining_time":0.7838267396},
{"learn":[4.812340486],"iteration":191,"passed_time":0.1855890105,"remaining_time":0.781020419},
{"learn":[4.806402747],"iteration":192,"passed_time":0.1860901217,"remaining_time":0.7781074},
{"learn":[4.801521788],"iteration":193,"passed_time":0.1866070311,"remaining_time":0.7752848817},
{"learn":[4.797601172],"iteration":194,"passed_time":0.1871044558,"remaining_time":0.7724055739},
{"learn":[4.792694629],"iteration":195,"passed_time":0.1876415051,"remaining_time":0.7697131126},
{"learn":[4.789794613],"iteration":196,"passed_time":0.1881571611,"remaining_time":0.7669553319},
{"learn":[4.785367055],"iteration":197,"passed_time":0.1886708099,"remaining_time":0.7642120685},
{"learn":[4.780376856],"iteration":198,"passed_time":0.1892036036,"remaining_time":0.7615682738},
{"learn":[4.776691261],"iteration":199,"passed_time":0.1897204472,"remaining_time":0.7588817887},
{"learn":[4.773470753],"iteration":200,"passed_time":0.1902398962,"remaining_time":0.7562272489},
{"learn":[4.77207327],"iteration":201,"passed_time":0.1907011406,"remaining_time":0.7533639117},
{"learn":[4.767347177],"iteration":202,"passed_time":0.1911911363,"remaining_time":0.7506371214},
{"learn":[4.763983068],"iteration":203,"passed_time":0.1917046186,"remaining_time":0.7480239041},
{"learn":[4.761588849],"iteration":204,"passed_time":0.1922073422,"remaining_time":0.745389449},
{"learn":[4.758558086],"iteration":205,"passed_time":0.1926644684,"remaining_time":0.7425999412},
{"learn":[4.753678804],"iteration":206,"passed_time":0.1931767406,"remaining_time":0.7400442285},
{"learn":[4.746510889],"iteration":207,"passed_time":0.193677349,"remaining_time":0.7374637519},
{"learn":[4.744840601],"iteration":208,"passed_time":0.1941915688,"remaining_time":0.7349546933},
{"learn":[4.741702222],"iteration":209,"passed_time":0.1946620186,"remaining_time":0.7322999747},
{"learn":[4.739352853],"iteration":210,"passed_time":0.1951768484,"remaining_time":0.7298319118},
{"learn":[4.735539287],"iteration":211,"passed_time":0.195683637,"remaining_time":0.7273523865},
{"learn":[4.730726751],"iteration":212,"passed_time":0.1961561599,"remaining_time":0.7247647785},
{"learn":[4.726416092],"iteration":213,"passed_time":0.1966480527,"remaining_time":0.7222680813},
{"learn":[4.721293082],"iteration":214,"passed_time":0.1971565232,"remaining_time":0.7198505614},
{"learn":[4.718443695],"iteration":215,"passed_time":0.1976280258,"remaining_time":0.7173165381},
{"learn":[4.711627962],"iteration":216,"passed_time":0.1980705972,"remaining_time":0.7146971319},
{"learn":[4.709790764],"iteration":217,"passed_time":0.1985926309,"remaining_time":0.7123827404},
{"learn":[4.706913073],"iteration":218,"passed_time":0.1991158587,"remaining_time":0.7100889755},
{"learn":[4.703846389],"iteration":219,"passed_time":0.1996878908,"remaining_time":0.7079843401},
{"learn":[4.701001135],"iteration":220,"passed_time":0.2002560622,"remaining_time":0.705879966},
{"learn":[4.700380864],"iteration":221,"passed_time":0.2007158023,"remaining_time":0.7034094332},
{"learn":[4.695837486],"iteration":222,"passed_time":0.2012422133,"remaining_time":0.7011892364},
{"learn":[4.691242996],"iteration":223,"passed_time":0.201757342,"remaining_time":0.6989450776},
{"learn":[4.690284609],"iteration":224,"passed_time":0.2022772364,"remaining_time":0.6967327033},
{"learn":[4.68827119],"iteration":225,"passed_time":0.2028308454,"remaining_time":0.6946507716},
{"learn":[4.686922425],"iteration":226,"passed_time":0.2034886467,"remaining_time":0.6929371098},
{"learn":[4.686085874],"iteration":227,"passed_time":0.204076172,"remaining_time":0.6909947578},
{"learn":[4.683230741],"iteration":228,"passed_time":0.2045698321,"remaining_time":0.688748212},
{"learn":[4.6773487],"iteration":229,"passed_time":0.2051869254,"remaining_time":0.6869301415},
{"learn":[4.671462906],"iteration":230,"passed_time":0.2056508839,"remaining_time":0.6846126827},
{"learn":[4.664799601],"iteration":231,"passed_time":0.2061973483,"remaining_time":0.6825843254},
{"learn":[4.660979386],"iteration":232,"passed_time":0.2066964523,"remaining_time":0.680412785},
{"learn":[4.656281279],"iteration":233,"passed_time":0.207293992,"remaining_time":0.6785777687},
{"learn":[4.651997094],"iteration":234,"passed_time":0.2077686381,"remaining_time":0.6763532262},
{"learn":[4.650151977],"iteration":235,"passed_time":0.2082832379,"remaining_time":0.674272855},
{"learn":[4.648478046],"iteration":236,"passed_time":0.2087661564,"remaining_time":0.672103702},
{"learn":[4.646364602],"iteration":237,"passed_time":0.2093067357,"remaining_time":0.6701333304},
{"learn":[4.642635873],"iteration":238,"passed_time":0.2098714063,"remaining_time":0.6682516325},
{"learn":[4.640860821],"iteration":239,"passed_time":0.2103746924,"remaining_time":0.6661865258},
{"learn":[4.639446822],"iteration":240,"passed_time":0.2108357864,"remaining_time":0.6640015014},
{"learn":[4.637120072],"iteration":241,"passed_time":0.2114705703,"remaining_time":0.6623747614},
{"learn":[4.633769267],"iteration":242,"passed_time":0.2119726547,"remaining_time":0.6603427967},
{"learn":[4.630491517],"iteration":243,"passed_time":0.2124881003,"remaining_time":0.6583647697},
{"learn":[4.627813333],"iteration":244,"passed_time":0.2129698806,"remaining_time":0.6562949383},
{"learn":[4.622496304],"iteration":245,"passed_time":0.213515652,"remaining_time":0.6544341529},
{"learn":[4.618979301],"iteration":246,"passed_time":0.2140089237,"remaining_time":0.6524239656},
{"learn":[4.616563458],"iteration":247,"passed_time":0.2145312241,"remaining_time":0.6505140344},
{"learn":[4.614759385],"iteration":248,"passed_time":0.2150420322,"remaining_time":0.6485805869},
{"learn":[4.61251363],"iteration":249,"passed_time":0.2155367072,"remaining_time":0.6466101215},
{"learn":[4.608796693],"iteration":250,"passed_time":0.2160189759,"remaining_time":0.6446143941},
{"learn":[4.60847774],"iteration":251,"passed_time":0.2164815865,"remaining_time":0.6425723282},
{"learn":[4.605195659],"iteration":252,"passed_time":0.2170319326,"remaining_time":0.6408017932},
{"learn":[4.60103766],"iteration":253,"passed_time":0.2175367595,"remaining_time":0.6389071755},
{"learn":[4.599325598],"iteration":254,"passed_time":0.21797182,"remaining_time":0.6368196311},
{"learn":[4.597012808],"iteration":255,"passed_time":0.2185886627,"remaining_time":0.6352733009},
{"learn":[4.594161533],"iteration":256,"passed_time":0.2191475177,"remaining_time":0.633566559},
{"learn":[4.592197259],"iteration":257,"passed_time":0.2196827415,"remaining_time":0.6318007527},
{"learn":[4.58952828],"iteration":258,"passed_time":0.2202207449,"remaining_time":0.6300524013},
{"learn":[4.585816572],"iteration":259,"passed_time":0.220788464,"remaining_time":0.6283979359},
{"learn":[4.582934052],"iteration":260,"passed_time":0.2212546995,"remaining_time":0.6264644557},
{"learn":[4.582234842],"iteration":261,"passed_time":0.2217542222,"remaining_time":0.6246359388},
{"learn":[4.57571562],"iteration":262,"passed_time":0.2222081582,"remaining_time":0.6226897817},
{"learn":[4.571197349],"iteration":263,"passed_time":0.2227595452,"remaining_time":0.621026611},
{"learn":[4.56723703],"iteration":264,"passed_time":0.2232800336,"remaining_time":0.619286131},
{"learn":[4.560335567],"iteration":265,"passed_time":0.2237406669,"remaining_time":0.6173896597},
{"learn":[4.554709345],"iteration":266,"passed_time":0.2242063219,"remaining_time":0.6155177301},
{"learn":[4.552806306],"iteration":267,"passed_time":0.2247150718,"remaining_time":0.6137740019},
{"learn":[4.550766241],"iteration":268,"passed_time":0.2252579775,"remaining_time":0.6121322733},
{"learn":[4.549216045],"iteration":269,"passed_time":0.2257225739,"remaining_time":0.6102869591},
{"learn":[4.547687452],"iteration":270,"passed_time":0.2262261115,"remaining_time":0.6085565876},
{"learn":[4.545642435],"iteration":271,"passed_time":0.2267268534,"remaining_time":0.6068277546},
{"learn":[4.543930359],"iteration":272,"passed_time":0.2271952118,"remaining_time":0.6050216811},
{"learn":[4.541029943],"iteration":273,"passed_time":0.2277305098,"remaining_time":0.6034027377},
{"learn":[4.537781449],"iteration":274,"passed_time":0.2281929513,"remaining_time":0.6015995989},
{"learn":[4.53066128],"iteration":275,"passed_time":0.2286969484,"remaining_time":0.5999151836},
{"learn":[4.526763956],"iteration":276,"passed_time":0.2291998668,"remaining_time":0.5982364754},
{"learn":[4.522036004],"iteration":277,"passed_time":0.2297393378,"remaining_time":0.5966611578},
{"learn":[4.515307629],"iteration":278,"passed_time":0.2303247834,"remaining_time":0.5952120748},
{"learn":[4.51109143],"iteration":279,"passed_time":0.2307936294,"remaining_time":0.5934693327},
{"learn":[4.508233494],"iteration":280,"passed_time":0.2313187228,"remaining_time":0.5918795789},
{"learn":[4.502555629],"iteration":281,"passed_time":0.2318474147,"remaining_time":0.5903065381},
{"learn":[4.500081355],"iteration":282,"passed_time":0.2323867678,"remaining_time":0.5887678888},
{"learn":[4.495281743],"iteration":283,"passed_time":0.232914777,"remaining_time":0.5872076772},
{"learn":[4.492138869],"iteration":284,"passed_time":0.2334925235,"remaining_time":0.5857794889},
{"learn":[4.491708261],"iteration":285,"passed_time":0.2339145563,"remaining_time":0.5839685077},
{"learn":[4.489398865],"iteration":286,"passed_time":0.2344205144,"remaining_time":0.582375703},
{"learn":[4.485796373],"iteration":287,"passed_time":0.2349567834,"remaining_time":0.5808653811},
{"learn":[4.479542205],"iteration":288,"passed_time":0.2354325695,"remaining_time":0.5792129998},
{"learn":[4.475986993],"iteration":289,"passed_time":0.2359493301,"remaining_time":0.5776690495},
{"learn":[4.468661855],"iteration":290,"passed_time":0.2364577795,"remaining_time":0.5761119096},
{"learn":[4.463785664],"iteration":291,"passed_time":0.2369367333,"remaining_time":0.5744904355},
{"learn":[4.460445831],"iteration":292,"passed_time":0.2374654137,"remaining_time":0.5729967492},
{"learn":[4.45692492],"iteration":293,"passed_time":0.2379636268,"remaining_time":0.5714364643},
{"learn":[4.454031688],"iteration":294,"passed_time":0.2384658279,"remaining_time":0.5698929108},
{"learn":[4.451672391],"iteration":295,"passed_time":0.2389595588,"remaining_time":0.568336248},
{"learn":[4.45031553],"iteration":296,"passed_time":0.2394579747,"remaining_time":0.5667978324},
{"learn":[4.446782666],"iteration":297,"passed_time":0.2400325081,"remaining_time":0.5654457071},
{"learn":[4.444369689],"iteration":298,"passed_time":0.2405162368,"remaining_time":0.563885893},
{"learn":[4.44411683],"iteration":299,"passed_time":0.2410240755,"remaining_time":0.5623895095},
{"learn":[4.440876943],"iteration":300,"passed_time":0.2414646523,"remaining_time":0.5607434949},
{"learn":[4.439336453],"iteration":301,"passed_time":0.2419538402,"remaining_time":0.559217816},
{"learn":[4.436666901],"iteration":302,"passed_time":0.2424842538,"remaining_time":0.5577938116},
{"learn":[4.433043336],"iteration":303,"passed_time":0.2429320659,"remaining_time":0.556186572},
{"learn":[4.431419305],"iteration":304,"passed_time":0.2434701626,"remaining_time":0.5547926657},
{"learn":[4.428859646],"iteration":305,"passed_time":0.2439866985,"remaining_time":0.5533554535},
{"learn":[4.424552441],"iteration":306,"passed_time":0.2444735807,"remaining_time":0.5518573009},
{"learn":[4.422706391],"iteration":307,"passed_time":0.2449243563,"remaining_time":0.5502845928},
{"learn":[4.421427994],"iteration":308,"passed_time":0.24543128,"remaining_time":0.548844707},
{"learn":[4.418733158],"iteration":309,"passed_time":0.2459026024,"remaining_time":0.5473315988},
{"learn":[4.415656941],"iteration":310,"passed_time":0.2463986241,"remaining_time":0.54587991},
{"learn":[4.410747417],"iteration":311,"passed_time":0.2469302536,"remaining_time":0.5445128669},
{"learn":[4.408126521],"iteration":312,"passed_time":0.247439767,"remaining_time":0.5431026195},
{"learn":[4.407843853],"iteration":313,"passed_time":0.2479570943,"remaining_time":0.5417151805},
{"learn":[4.405219398],"iteration":314,"passed_time":0.2484622751,"remaining_time":0.5403068522},
{"learn":[4.402708465],"iteration":315,"passed_time":0.2489983187,"remaining_time":0.5389710442},
{"learn":[4.40104971],"iteration":316,"passed_time":0.2495394165,"remaining_time":0.5376511718},
{"learn":[4.400830038],"iteration":317,"passed_time":0.2500676909,"remaining_time":0.5363086956},
{"learn":[4.39784288],"iteration":318,"passed_time":0.2506077413,"remaining_time":0.5349964634},
{"learn":[4.393741845],"iteration":319,"passed_time":0.251158392,"remaining_time":0.5337115831},
{"learn":[4.393425936],"iteration":320,"passed_time":0.2516259085,"remaining_time":0.5322554264},
{"learn":[4.390505974],"iteration":321,"passed_time":0.2521225398,"remaining_time":0.5308667143},
{"learn":[4.390305136],"iteration":322,"passed_time":0.2527057322,"remaining_time":0.5296649557},
{"learn":[4.38568203],"iteration":323,"passed_time":0.2532609543,"remaining_time":0.5284086577},
{"learn":[4.383057135],"iteration":324,"passed_time":0.2537613227,"remaining_time":0.5270427471},
{"learn":[4.380662684],"iteration":325,"passed_time":0.2542590911,"remaining_time":0.5256767711},
{"learn":[4.37805727],"iteration":326,"passed_time":0.2547533822,"remaining_time":0.5243089487},
{"learn":[4.373708319],"iteration":327,"passed_time":0.2553554052,"remaining_time":0.5231671717},
{"learn":[4.36887921],"iteration":328,"passed_time":0.2559029523,"remaining_time":0.5219175714},
{"learn":[4.367895929],"iteration":329,"passed_time":0.2563917824,"remaining_time":0.5205530127},
{"learn":[4.362140573],"iteration":330,"passed_time":0.2569982405,"remaining_time":0.5194314891},
{"learn":[4.361931924],"iteration":331,"passed_time":0.2575786499,"remaining_time":0.5182606569},
{"learn":[4.359656377],"iteration":332,"passed_time":0.2581401248,"remaining_time":0.5170554453},
{"learn":[4.354281355],"iteration":333,"passed_time":0.2587287404,"remaining_time":0.5159082069},
{"learn":[4.348589447],"iteration":334,"passed_time":0.2593247784,"remaining_time":0.5147790378},
{"learn":[4.346355698],"iteration":335,"passed_time":0.2598017184,"remaining_time":0.5134176816},
{"learn":[4.343894047],"iteration":336,"passed_time":0.2602926223,"remaining_time":0.5120890463},
{"learn":[4.341561356],"iteration":337,"passed_time":0.2607992253,"remaining_time":0.5107961158},
{"learn":[4.338869061],"iteration":338,"passed_time":0.2612634666,"remaining_time":0.5094252254},
{"learn":[4.333720063],"iteration":339,"passed_time":0.2617103522,"remaining_time":0.5080259777},
{"learn":[4.330892223],"iteration":340,"passed_time":0.2623122539,"remaining_time":0.5069318924},
{"learn":[4.328311474],"iteration":341,"passed_time":0.2628791697,"remaining_time":0.5057733732},
{"learn":[4.324580133],"iteration":342,"passed_time":0.2634091283,"remaining_time":0.504547514},
{"learn":[4.323354432],"iteration":343,"passed_time":0.2639506295,"remaining_time":0.5033477121},
{"learn":[4.323159553],"iteration":344,"passed_time":0.2644192217,"remaining_time":0.502013305},
{"learn":[4.318639682],"iteration":345,"passed_time":0.2649026756,"remaining_time":0.5007119938},
{"learn":[4.312712208],"iteration":346,"passed_time":0.2653672556,"remaining_time":0.4993798788},
{"learn":[4.311461062],"iteration":347,"passed_time":0.2658693776,"remaining_time":0.4981230867},
{"learn":[4.311178356],"iteration":348,"passed_time":0.2663514477,"remaining_time":0.4968332161},
{"learn":[4.311102505],"iteration":349,"passed_time":0.2669454723,"remaining_time":0.4957558771},
{"learn":[4.310232308],"iteration":350,"passed_time":0.2674811316,"remaining_time":0.4945733744},
{"learn":[4.305128197],"iteration":351,"passed_time":0.2680014152,"remaining_time":0.4933662417},
{"learn":[4.304595496],"iteration":352,"passed_time":0.2684906667,"remaining_time":0.4921061227},
{"learn":[4.3004992],"iteration":353,"passed_time":0.2689605834,"remaining_time":0.4908150759},
{"learn":[4.297581524],"iteration":354,"passed_time":0.2694661439,"remaining_time":0.4895934163},
{"learn":[4.297355825],"iteration":355,"passed_time":0.2699414092,"remaining_time":0.4883209762},
{"learn":[4.295758715],"iteration":356,"passed_time":0.2704502563,"remaining_time":0.4871134868},
{"learn":[4.292500657],"iteration":357,"passed_time":0.2709673651,"remaining_time":0.4859247161},
{"learn":[4.290797586],"iteration":358,"passed_time":0.2714714985,"remaining_time":0.4847165195},
{"learn":[4.286410608],"iteration":359,"passed_time":0.2719926524,"remaining_time":0.4835424931},
{"learn":[4.280278245],"iteration":360,"passed_time":0.272502682,"remaining_time":0.4823523928},
{"learn":[4.279941283],"iteration":361,"passed_time":0.2729672203,"remaining_time":0.4810858744},
{"learn":[4.274426275],"iteration":362,"passed_time":0.2734382977,"remaining_time":0.4798352497},
{"learn":[4.273567658],"iteration":363,"passed_time":0.2739114846,"remaining_time":0.478592594},
{"learn":[4.269488271],"iteration":364,"passed_time":0.274392704,"remaining_time":0.4773681288},
{"learn":[4.266838205],"iteration":365,"passed_time":0.2748763458,"remaining_time":0.4761519214},
{"learn":[4.263456509],"iteration":366,"passed_time":0.2753568123,"remaining_time":0.4749342295},
{"learn":[4.260360204],"iteration":367,"passed_time":0.2759210179,"remaining_time":0.4738643568},
{"learn":[4.255120549],"iteration":368,"passed_time":0.276441424,"remaining_time":0.4727223267},
{"learn":[4.252582211],"iteration":369,"passed_time":0.2768920183,"remaining_time":0.4714647879},
{"learn":[4.247857931],"iteration":370,"passed_time":0.2774695632,"remaining_time":0.4704268335},
{"learn":[4.245288911],"iteration":371,"passed_time":0.2780016733,"remaining_time":0.4693146528},
{"learn":[4.24048515],"iteration":372,"passed_time":0.2785510072,"remaining_time":0.4682345349},
{"learn":[4.2378365],"iteration":373,"passed_time":0.2790521835,"remaining_time":0.4670766494},
{"learn":[4.236751063],"iteration":374,"passed_time":0.2795751315,"remaining_time":0.4659585525},
{"learn":[4.233240093],"iteration":375,"passed_time":0.280121971,"remaining_time":0.464883271},
{"learn":[4.230358421],"iteration":376,"passed_time":0.280690891,"remaining_time":0.4638472814},
{"learn":[4.225853583],"iteration":377,"passed_time":0.2812560502,"remaining_time":0.4628075747},
{"learn":[4.224702126],"iteration":378,"passed_time":0.2818292606,"remaining_time":0.4617835643},
{"learn":[4.224361982],"iteration":379,"passed_time":0.2824302332,"remaining_time":0.4608072225},
{"learn":[4.223787954],"iteration":380,"passed_time":0.2830081753,"remaining_time":0.4597954344},
{"learn":[4.22144054],"iteration":381,"passed_time":0.2836183494,"remaining_time":0.4588380626},
{"learn":[4.217739335],"iteration":382,"passed_time":0.2842142718,"remaining_time":0.4578595449},
{"learn":[4.215611665],"iteration":383,"passed_time":0.2847754529,"remaining_time":0.456827289},
{"learn":[4.210236863],"iteration":384,"passed_time":0.285307971,"remaining_time":0.455751694},
{"learn":[4.208454294],"iteration":385,"passed_time":0.285850949,"remaining_time":0.4546955511},
{"learn":[4.207446501],"iteration":386,"passed_time":0.2863725687,"remaining_time":0.453608229},
{"learn":[4.204985442],"iteration":387,"passed_time":0.2868550839,"remaining_time":0.4524621426},
{"learn":[4.202796622],"iteration":388,"passed_time":0.2873792362,"remaining_time":0.4513848671},
{"learn":[4.199774004],"iteration":389,"passed_time":0.2878802694,"remaining_time":0.4502742675},
{"learn":[4.199458358],"iteration":390,"passed_time":0.2883362046,"remaining_time":0.4490965437},
{"learn":[4.19751254],"iteration":391,"passed_time":0.2888456211,"remaining_time":0.4480054532},
{"learn":[4.195201346],"iteration":392,"passed_time":0.2893413421,"remaining_time":0.4468961695},
{"learn":[4.190593508],"iteration":393,"passed_time":0.2898273432,"remaining_time":0.4457750507},
{"learn":[4.187212054],"iteration":394,"passed_time":0.2903431887,"remaining_time":0.4447028587},
{"learn":[4.184984466],"iteration":395,"passed_time":0.2909064773,"remaining_time":0.4437058391},
{"learn":[4.182832144],"iteration":396,"passed_time":0.2913954298,"remaining_time":0.4425980962},
{"learn":[4.179752812],"iteration":397,"passed_time":0.2919046183,"remaining_time":0.4415240709},
{"learn":[4.17878934],"iteration":398,"passed_time":0.2924635855,"remaining_time":0.4405278568},
{"learn":[4.174548229],"iteration":399,"passed_time":0.2930139779,"remaining_time":0.4395209668},
{"learn":[4.168872556],"iteration":400,"passed_time":0.2936881193,"remaining_time":0.4387012056},
{"learn":[4.163926494],"iteration":401,"passed_time":0.2943431827,"remaining_time":0.4378537892},
{"learn":[4.159485076],"iteration":402,"passed_time":0.2948850077,"remaining_time":0.4368395771},
{"learn":[4.155926102],"iteration":403,"passed_time":0.2954469228,"remaining_time":0.4358573415},
{"learn":[4.153540115],"iteration":404,"passed_time":0.2960663348,"remaining_time":0.4349616524},
{"learn":[4.150983044],"iteration":405,"passed_time":0.2965918599,"remaining_time":0.4339299626},
{"learn":[4.146539132],"iteration":406,"passed_time":0.2971615285,"remaining_time":0.4329650771},
{"learn":[4.144869174],"iteration":407,"passed_time":0.2977137728,"remaining_time":0.4319768468},
{"learn":[4.142825962],"iteration":408,"passed_time":0.2981960775,"remaining_time":0.4308896865},
{"learn":[4.142467378],"iteration":409,"passed_time":0.2986893824,"remaining_time":0.4298213064},
{"learn":[4.141800768],"iteration":410,"passed_time":0.299212733,"remaining_time":0.4287987828},
{"learn":[4.140107084],"iteration":411,"passed_time":0.2997813958,"remaining_time":0.4278433513},
{"learn":[4.136243196],"iteration":412,"passed_time":0.3005285166,"remaining_time":0.4271434364},
{"learn":[4.133618439],"iteration":413,"passed_time":0.3010616823,"remaining_time":0.4261404488},
{"learn":[4.131053025],"iteration":414,"passed_time":0.301718066,"remaining_time":0.4253134184},
{"learn":[4.128379975],"iteration":415,"passed_time":0.3022743528,"remaining_time":0.4243466876},
{"learn":[4.127068571],"iteration":416,"passed_time":0.3027885596,"remaining_time":0.4233230941},
{"learn":[4.125969877],"iteration":417,"passed_time":0.3032714704,"remaining_time":0.4222583632},
{"learn":[4.123893633],"iteration":418,"passed_time":0.3037782288,"remaining_time":0.4212294771},
{"learn":[4.119643722],"iteration":419,"passed_time":0.304323635,"remaining_time":0.4202564484},
{"learn":[4.11465686],"iteration":420,"passed_time":0.3048353723,"remaining_time":0.4192391462},
{"learn":[4.111565986],"iteration":421,"passed_time":0.3053652027,"remaining_time":0.4182490217},
{"learn":[4.106322452],"iteration":422,"passed_time":0.305845623,"remaining_time":0.4171936748},
{"learn":[4.104222175],"iteration":423,"passed_time":0.3064123746,"remaining_time":0.4162583202},
{"learn":[4.103008002],"iteration":424,"passed_time":0.3069432617,"remaining_time":0.4152761775},
{"learn":[4.099176337],"iteration":425,"passed_time":0.3076199759,"remaining_time":0.4144926436},
{"learn":[4.096525716],"iteration":426,"passed_time":0.3081933723,"remaining_time":0.4135709657},
{"learn":[4.094967724],"iteration":427,"passed_time":0.3086840657,"remaining_time":0.4125403869},
{"learn":[4.094683584],"iteration":428,"passed_time":0.3092497646,"remaining_time":0.4116121575},
{"learn":[4.091096563],"iteration":429,"passed_time":0.3097956538,"remaining_time":0.410659355},
{"learn":[4.089178677],"iteration":430,"passed_time":0.3103303774,"remaining_time":0.4096937001},
{"learn":[4.085335077],"iteration":431,"passed_time":0.3108149148,"remaining_time":0.4086640546},
{"learn":[4.084852122],"iteration":432,"passed_time":0.3113690412,"remaining_time":0.4077280516},
{"learn":[4.080322952],"iteration":433,"passed_time":0.3118027776,"remaining_time":0.4066368021},
{"learn":[4.077449519],"iteration":434,"passed_time":0.3123545956,"remaining_time":0.405701946},
{"learn":[4.076568374],"iteration":435,"passed_time":0.3128900555,"remaining_time":0.4047476865},
{"learn":[4.076071793],"iteration":436,"passed_time":0.3133968468,"remaining_time":0.403758409},
{"learn":[4.075027644],"iteration":437,"passed_time":0.3138794101,"remaining_time":0.4027402477},
{"learn":[4.07020837],"iteration":438,"passed_time":0.3143838948,"remaining_time":0.4017525399},
{"learn":[4.06833694],"iteration":439,"passed_time":0.3149496048,"remaining_time":0.4008449515},
{"learn":[4.063936568],"iteration":440,"passed_time":0.3156024888,"remaining_time":0.4000494132},
{"learn":[4.061734926],"iteration":441,"passed_time":0.3161543492,"remaining_time":0.3991269839},
{"learn":[4.060815619],"iteration":442,"passed_time":0.3168537617,"remaining_time":0.39839175},
{"learn":[4.056407489],"iteration":443,"passed_time":0.3174317727,"remaining_time":0.3975046523},
{"learn":[4.05238936],"iteration":444,"passed_time":0.3179166357,"remaining_time":0.3965027704},
{"learn":[4.049685254],"iteration":445,"passed_time":0.3184431099,"remaining_time":0.3955548943},
{"learn":[4.045162016],"iteration":446,"passed_time":0.3190052975,"remaining_time":0.3946530861},
{"learn":[4.042955482],"iteration":447,"passed_time":0.3195052774,"remaining_time":0.3936761454},
{"learn":[4.041467663],"iteration":448,"passed_time":0.3200732457,"remaining_time":0.3927847625},
{"learn":[4.038920476],"iteration":449,"passed_time":0.3206001362,"remaining_time":0.3918446109},
{"learn":[4.036694383],"iteration":450,"passed_time":0.3211730493,"remaining_time":0.390962315},
{"learn":[4.034999007],"iteration":451,"passed_time":0.3217318638,"remaining_time":0.390064295},
{"learn":[4.031928018],"iteration":452,"passed_time":0.3222766439,"remaining_time":0.3891508261},
{"learn":[4.028718143],"iteration":453,"passed_time":0.3228081575,"remaining_time":0.3882230264},
{"learn":[4.027401978],"iteration":454,"passed_time":0.323399326,"remaining_time":0.3873684235},
{"learn":[4.025930598],"iteration":455,"passed_time":0.3239360695,"remaining_time":0.3864500479},
{"learn":[4.021074523],"iteration":456,"passed_time":0.3244608495,"remaining_time":0.3855191275},
{"learn":[4.020268486],"iteration":457,"passed_time":0.3249390635,"remaining_time":0.3845348743},
{"learn":[4.017986361],"iteration":458,"passed_time":0.3254206296,"remaining_time":0.3835567769},
{"learn":[4.014814804],"iteration":459,"passed_time":0.3259862316,"remaining_time":0.3826794892},
{"learn":[4.009704796],"iteration":460,"passed_time":0.3265010763,"remaining_time":0.3817442085},
{"learn":[4.008440457],"iteration":461,"passed_time":0.3270308298,"remaining_time":0.3808281092},
{"learn":[4.004854849],"iteration":462,"passed_time":0.3275519367,"remaining_time":0.3799036501},
{"learn":[4.000898028],"iteration":463,"passed_time":0.3280968638,"remaining_time":0.3790084461},
{"learn":[3.996617985],"iteration":464,"passed_time":0.3285561293,"remaining_time":0.3780161917},
{"learn":[3.995443319],"iteration":465,"passed_time":0.3291378566,"remaining_time":0.3771665568},
{"learn":[3.990771995],"iteration":466,"passed_time":0.3296884278,"remaining_time":0.3762825097},
{"learn":[3.989249359],"iteration":467,"passed_time":0.3302871784,"remaining_time":0.3754546557},
{"learn":[3.986599538],"iteration":468,"passed_time":0.3308219778,"remaining_time":0.3745553735},
{"learn":[3.985628919],"iteration":469,"passed_time":0.3313732515,"remaining_time":0.3736762198},
{"learn":[3.985086112],"iteration":470,"passed_time":0.3319404065,"remaining_time":0.3728162952},
{"learn":[3.98466839],"iteration":471,"passed_time":0.3323835543,"remaining_time":0.3718188912},
{"learn":[3.984233894],"iteration":472,"passed_time":0.3329667987,"remaining_time":0.3709799216},
{"learn":[3.981855845],"iteration":473,"passed_time":0.3335214058,"remaining_time":0.370110252},
{"learn":[3.978684264],"iteration":474,"passed_time":0.3340579495,"remaining_time":0.3692219442},
{"learn":[3.974361269],"iteration":475,"passed_time":0.3346329674,"remaining_time":0.3683774683},
{"learn":[3.972074049],"iteration":476,"passed_time":0.3351211105,"remaining_time":0.3674388696},
{"learn":[3.97191982],"iteration":477,"passed_time":0.3355876783,"remaining_time":0.3664785943},
{"learn":[3.969616848],"iteration":478,"passed_time":0.3360978537,"remaining_time":0.3655678117},
{"learn":[3.968533527],"iteration":479,"passed_time":0.3365956875,"remaining_time":0.3646453281},
{"learn":[3.967568753],"iteration":480,"passed_time":0.3371273503,"remaining_time":0.3637611119},
{"learn":[3.966232553],"iteration":481,"passed_time":0.3376438495,"remaining_time":0.3628620623},
{"learn":[3.961522393],"iteration":482,"passed_time":0.3381628725,"remaining_time":0.3619672983},
{"learn":[3.955829553],"iteration":483,"passed_time":0.3386751884,"remaining_time":0.3610669364},
{"learn":[3.954248095],"iteration":484,"passed_time":0.3391865701,"remaining_time":0.3601671827},
{"learn":[3.951922606],"iteration":485,"passed_time":0.3397206041,"remaining_time":0.3592929846},
{"learn":[3.94978202],"iteration":486,"passed_time":0.3402772077,"remaining_time":0.358443958},
{"learn":[3.949518999],"iteration":487,"passed_time":0.3407437827,"remaining_time":0.3575016737},
{"learn":[3.945431216],"iteration":488,"passed_time":0.3412712626,"remaining_time":0.3566249799},
{"learn":[3.943249086],"iteration":489,"passed_time":0.3417748698,"remaining_time":0.3557248645},
{"learn":[3.941981548],"iteration":490,"passed_time":0.3422525541,"remaining_time":0.354799491},
{"learn":[3.936600517],"iteration":491,"passed_time":0.342783752,"remaining_time":0.3539311911},
{"learn":[3.934476885],"iteration":492,"passed_time":0.3432989469,"remaining_time":0.3530478014},
{"learn":[3.93045798],"iteration":493,"passed_time":0.3437818447,"remaining_time":0.3521328207},
{"learn":[3.925977375],"iteration":494,"passed_time":0.3443746417,"remaining_time":0.3513317051},
{"learn":[3.92457993],"iteration":495,"passed_time":0.344941952,"remaining_time":0.3505055319},
{"learn":[3.919849146],"iteration":496,"passed_time":0.3454428348,"remaining_time":0.3496131708},
{"learn":[3.919681964],"iteration":497,"passed_time":0.3459089934,"remaining_time":0.3486873789},
{"learn":[3.917633027],"iteration":498,"passed_time":0.3463962563,"remaining_time":0.3477846181},
{"learn":[3.916616419],"iteration":499,"passed_time":0.3469205227,"remaining_time":0.3469205227},
{"learn":[3.912896166],"iteration":500,"passed_time":0.3475373948,"remaining_time":0.34615002},
{"learn":[3.912769674],"iteration":501,"passed_time":0.3480276722,"remaining_time":0.3452545434},
{"learn":[3.909373788],"iteration":502,"passed_time":0.3485268267,"remaining_time":0.3443694491},
{"learn":[3.906706036],"iteration":503,"passed_time":0.3490814794,"remaining_time":0.3435405035},
{"learn":[3.903895664],"iteration":504,"passed_time":0.3495931833,"remaining_time":0.342670546},
{"learn":[3.902982967],"iteration":505,"passed_time":0.3501800744,"remaining_time":0.3418754086},
{"learn":[3.900905528],"iteration":506,"passed_time":0.3506962345,"remaining_time":0.3410123148},
{"learn":[3.897463465],"iteration":507,"passed_time":0.3512229762,"remaining_time":0.3401608352},
{"learn":[3.895918033],"iteration":508,"passed_time":0.3516989908,"remaining_time":0.3392616984},
{"learn":[3.893921936],"iteration":509,"passed_time":0.3522820898,"remaining_time":0.3384671059},
{"learn":[3.890237934],"iteration":510,"passed_time":0.352767383,"remaining_time":0.3375797461},
{"learn":[3.887311613],"iteration":511,"passed_time":0.353293117,"remaining_time":0.3367325021},
{"learn":[3.884869735],"iteration":512,"passed_time":0.3539366318,"remaining_time":0.335998323},
{"learn":[3.882101231],"iteration":513,"passed_time":0.3544350327,"remaining_time":0.3351272878},
{"learn":[3.88060368],"iteration":514,"passed_time":0.3549797413,"remaining_time":0.3343013098},
{"learn":[3.877726076],"iteration":515,"passed_time":0.3554744837,"remaining_time":0.3334295545},
{"learn":[3.874938145],"iteration":516,"passed_time":0.3559994929,"remaining_time":0.332587534},
{"learn":[3.874340833],"iteration":517,"passed_time":0.3564888488,"remaining_time":0.331713562},
{"learn":[3.873105224],"iteration":518,"passed_time":0.3570458899,"remaining_time":0.3309038016},
{"learn":[3.869800236],"iteration":519,"passed_time":0.3575686212,"remaining_time":0.3300633427},
{"learn":[3.867932518],"iteration":520,"passed_time":0.3580400561,"remaining_time":0.3291769422},
{"learn":[3.866666962],"iteration":521,"passed_time":0.3585434306,"remaining_time":0.328321379},
{"learn":[3.865527652],"iteration":522,"passed_time":0.359093218,"remaining_time":0.3275094933},
{"learn":[3.861900081],"iteration":523,"passed_time":0.3596719699,"remaining_time":0.3267249192},
{"learn":[3.858502887],"iteration":524,"passed_time":0.3601942689,"remaining_time":0.3258900528},
{"learn":[3.858335097],"iteration":525,"passed_time":0.3607181147,"remaining_time":0.3250577687},
{"learn":[3.855719306],"iteration":526,"passed_time":0.3612132351,"remaining_time":0.3242008733},
{"learn":[3.855137428],"iteration":527,"passed_time":0.3617056151,"remaining_time":0.3233428984},
{"learn":[3.851985706],"iteration":528,"passed_time":0.3622079024,"remaining_time":0.3224951267},
{"learn":[3.851051809],"iteration":529,"passed_time":0.3627261317,"remaining_time":0.321662796},
{"learn":[3.850679146],"iteration":530,"passed_time":0.3632335605,"remaining_time":0.320822109},
{"learn":[3.848179484],"iteration":531,"passed_time":0.363709419,"remaining_time":0.3199549024},
{"learn":[3.844551071],"iteration":532,"passed_time":0.3641787227,"remaining_time":0.3190834212},
{"learn":[3.841604794],"iteration":533,"passed_time":0.3647063866,"remaining_time":0.3182643749},
{"learn":[3.83969656],"iteration":534,"passed_time":0.3652138453,"remaining_time":0.3174288562},
{"learn":[3.836811463],"iteration":535,"passed_time":0.3657089156,"remaining_time":0.3165838374},
{"learn":[3.834182551],"iteration":536,"passed_time":0.3661862988,"remaining_time":0.3157248722},
{"learn":[3.828012842],"iteration":537,"passed_time":0.3667006966,"remaining_time":0.3148991112},
{"learn":[3.826636176],"iteration":538,"passed_time":0.3673260649,"remaining_time":0.3141694173},
{"learn":[3.826189798],"iteration":539,"passed_time":0.3678738397,"remaining_time":0.3133740116},
{"learn":[3.824104738],"iteration":540,"passed_time":0.3684351873,"remaining_time":0.3125910369},
{"learn":[3.82300218],"iteration":541,"passed_time":0.3689274765,"remaining_time":0.3117505245},
{"learn":[3.817146402],"iteration":542,"passed_time":0.3694319509,"remaining_time":0.3109215499},
{"learn":[3.814638044],"iteration":543,"passed_time":0.3699155602,"remaining_time":0.3100762784},
{"learn":[3.812979573],"iteration":544,"passed_time":0.3703906579,"remaining_time":0.3092252282},
{"learn":[3.811938825],"iteration":545,"passed_time":0.3709681588,"remaining_time":0.3084607034},
{"learn":[3.811479418],"iteration":546,"passed_time":0.3715115872,"remaining_time":0.3076686454},
{"learn":[3.80742981],"iteration":547,"passed_time":0.3719893026,"remaining_time":0.3068232934},
{"learn":[3.805097043],"iteration":548,"passed_time":0.3725315103,"remaining_time":0.3060322607},
{"learn":[3.801577232],"iteration":549,"passed_time":0.372971177,"remaining_time":0.3051582357},
{"learn":[3.799762083],"iteration":550,"passed_time":0.3735136089,"remaining_time":0.3043695289},
{"learn":[3.796393455],"iteration":551,"passed_time":0.3740324743,"remaining_time":0.3035625878},
{"learn":[3.793486459],"iteration":552,"passed_time":0.3746297825,"remaining_time":0.3028200954},
{"learn":[3.792006091],"iteration":553,"passed_time":0.3751680594,"remaining_time":0.3020306038},
{"learn":[3.78932128],"iteration":554,"passed_time":0.3756970571,"remaining_time":0.3012345773},
{"learn":[3.787581812],"iteration":555,"passed_time":0.3762643174,"remaining_time":0.3004700664},
{"learn":[3.785308865],"iteration":556,"passed_time":0.3767876171,"remaining_time":0.2996713005},
{"learn":[3.78465475],"iteration":557,"passed_time":0.377295489,"remaining_time":0.2988613013},
{"learn":[3.780498869],"iteration":558,"passed_time":0.3778717633,"remaining_time":0.2981063464},
{"learn":[3.778734909],"iteration":559,"passed_time":0.3789035871,"remaining_time":0.2977099613},
{"learn":[3.778652349],"iteration":560,"passed_time":0.379758757,"remaining_time":0.2971730737},
{"learn":[3.777928006],"iteration":561,"passed_time":0.3802741482,"remaining_time":0.2963702437},
{"learn":[3.776131406],"iteration":562,"passed_time":0.3808315774,"remaining_time":0.2956010645},
{"learn":[3.772925617],"iteration":563,"passed_time":0.3813322022,"remaining_time":0.2947887237},
{"learn":[3.7727745],"iteration":564,"passed_time":0.3818463982,"remaining_time":0.2939879349},
{"learn":[3.771763073],"iteration":565,"passed_time":0.3823682066,"remaining_time":0.2931939958},
{"learn":[3.768738162],"iteration":566,"passed_time":0.3828707196,"remaining_time":0.2923862815},
{"learn":[3.767220794],"iteration":567,"passed_time":0.3833842257,"remaining_time":0.2915880026},
{"learn":[3.766691102],"iteration":568,"passed_time":0.3840129576,"remaining_time":0.2908780048},
{"learn":[3.766259335],"iteration":569,"passed_time":0.3845272149,"remaining_time":0.290081934},
{"learn":[3.76116362],"iteration":570,"passed_time":0.3850702714,"remaining_time":0.2893084876},
{"learn":[3.758633056],"iteration":571,"passed_time":0.3855749218,"remaining_time":0.2885071093},
{"learn":[3.754603809],"iteration":572,"passed_time":0.3861008587,"remaining_time":0.2877226294},
{"learn":[3.754070549],"iteration":573,"passed_time":0.3865839532,"remaining_time":0.2869072545},
{"learn":[3.750534319],"iteration":574,"passed_time":0.3870838605,"remaining_time":0.2861054621},
{"learn":[3.746491516],"iteration":575,"passed_time":0.3875782661,"remaining_time":0.2853006681},
{"learn":[3.744210544],"iteration":576,"passed_time":0.3880944235,"remaining_time":0.2845128962},
{"learn":[3.742929991],"iteration":577,"passed_time":0.3886121178,"remaining_time":0.2837271863},
{"learn":[3.740402992],"iteration":578,"passed_time":0.3891570728,"remaining_time":0.2829622239},
{"learn":[3.739644243],"iteration":579,"passed_time":0.3897534266,"remaining_time":0.2822352399},
{"learn":[3.737529404],"iteration":580,"passed_time":0.390267587,"remaining_time":0.2814494302},
{"learn":[3.737196923],"iteration":581,"passed_time":0.3907777234,"remaining_time":0.2806616639},
{"learn":[3.733954464],"iteration":582,"passed_time":0.3912908694,"remaining_time":0.2798770026},
{"learn":[3.731608623],"iteration":583,"passed_time":0.391840692,"remaining_time":0.279119397},
{"learn":[3.729843952],"iteration":584,"passed_time":0.3923444767,"remaining_time":0.2783298425},
{"learn":[3.727223798],"iteration":585,"passed_time":0.3928491643,"remaining_time":0.277541901},
{"learn":[3.725351667],"iteration":586,"passed_time":0.3933364371,"remaining_time":0.2767426721},
{"learn":[3.725026912],"iteration":587,"passed_time":0.3938579006,"remaining_time":0.275968461},
{"learn":[3.721974565],"iteration":588,"passed_time":0.3943755904,"remaining_time":0.2751924748},
{"learn":[3.720269493],"iteration":589,"passed_time":0.3949011625,"remaining_time":0.2744228418},
{"learn":[3.718907466],"iteration":590,"passed_time":0.3953928433,"remaining_time":0.2736305802},
{"learn":[3.715602912],"iteration":591,"passed_time":0.3959199815,"remaining_time":0.272863771},
{"learn":[3.714463059],"iteration":592,"passed_time":0.3966115475,"remaining_time":0.2722106236},
{"learn":[3.710802077],"iteration":593,"passed_time":0.3972154675,"remaining_time":0.2714974408},
{"learn":[3.708032435],"iteration":594,"passed_time":0.3977709399,"remaining_time":0.2707516482},
{"learn":[3.703788939],"iteration":595,"passed_time":0.3983429858,"remaining_time":0.2700177286},
{"learn":[3.702500944],"iteration":596,"passed_time":0.3988577819,"remaining_time":0.2692457054},
{"learn":[3.698196925],"iteration":597,"passed_time":0.3993336503,"remaining_time":0.2684483736},
{"learn":[3.69658891],"iteration":598,"passed_time":0.3998464411,"remaining_time":0.2676768329},
{"learn":[3.696124066],"iteration":599,"passed_time":0.4003661714,"remaining_time":0.2669107809},
{"learn":[3.693537052],"iteration":600,"passed_time":0.4009249113,"remaining_time":0.2661714469},
{"learn":[3.691343275],"iteration":601,"passed_time":0.4014138259,"remaining_time":0.2653865493},
{"learn":[3.690973831],"iteration":602,"passed_time":0.4019048113,"remaining_time":0.2646039968},
{"learn":[3.686151073],"iteration":603,"passed_time":0.4023917329,"remaining_time":0.2638197454},
{"learn":[3.683921982],"iteration":604,"passed_time":0.4028711137,"remaining_time":0.2630315536},
{"learn":[3.679975271],"iteration":605,"passed_time":0.4033636475,"remaining_time":0.2622529325},
{"learn":[3.674047638],"iteration":606,"passed_time":0.4038897222,"remaining_time":0.26149697},
{"learn":[3.673151794],"iteration":607,"passed_time":0.4044207918,"remaining_time":0.2607449842},
{"learn":[3.670953108],"iteration":608,"passed_time":0.404950631,"remaining_time":0.2599929339},
{"learn":[3.6703947],"iteration":609,"passed_time":0.4054539263,"remaining_time":0.2592246414},
{"learn":[3.668433805],"iteration":610,"passed_time":0.4059752742,"remaining_time":0.2584687098},
{"learn":[3.668304956],"iteration":611,"passed_time":0.4064629811,"remaining_time":0.2576922168},
{"learn":[3.667880012],"iteration":612,"passed_time":0.4069332568,"remaining_time":0.2569056613},
{"learn":[3.667282264],"iteration":613,"passed_time":0.4074687841,"remaining_time":0.2561611574},
{"learn":[3.664611483],"iteration":614,"passed_time":0.4079241567,"remaining_time":0.255367155},
{"learn":[3.662543394],"iteration":615,"passed_time":0.4084567701,"remaining_time":0.2546224022},
{"learn":[3.659041959],"iteration":616,"passed_time":0.4089485041,"remaining_time":0.2538529612},
{"learn":[3.656868545],"iteration":617,"passed_time":0.4094176658,"remaining_time":0.2530704666},
{"learn":[3.654785614],"iteration":618,"passed_time":0.4099471751,"remaining_time":0.2523261288},
{"learn":[3.654566096],"iteration":619,"passed_time":0.4103823605,"remaining_time":0.2515246725},
{"learn":[3.651007045],"iteration":620,"passed_time":0.4109164699,"remaining_time":0.2507847698},
{"learn":[3.648921786],"iteration":621,"passed_time":0.4114268634,"remaining_time":0.2500311164},
{"learn":[3.647655706],"iteration":622,"passed_time":0.4119587095,"remaining_time":0.2492912255},
{"learn":[3.647241144],"iteration":623,"passed_time":0.4124546857,"remaining_time":0.2485303876},
{"learn":[3.644195689],"iteration":624,"passed_time":0.4129227624,"remaining_time":0.2477536575},
{"learn":[3.642632246],"iteration":625,"passed_time":0.4134373098,"remaining_time":0.2470056771},
{"learn":[3.642523322],"iteration":626,"passed_time":0.4138249124,"remaining_time":0.2461829223},
{"learn":[3.641494659],"iteration":627,"passed_time":0.4143257155,"remaining_time":0.2454286086},
{"learn":[3.63976496],"iteration":628,"passed_time":0.4147953242,"remaining_time":0.2446567015},
{"learn":[3.637945652],"iteration":629,"passed_time":0.4152633622,"remaining_time":0.2438848318},
{"learn":[3.636233667],"iteration":630,"passed_time":0.4157909091,"remaining_time":0.243148725},
{"learn":[3.635304404],"iteration":631,"passed_time":0.4162717879,"remaining_time":0.2423861043},
{"learn":[3.632234951],"iteration":632,"passed_time":0.4168446979,"remaining_time":0.2416777316},
{"learn":[3.631630987],"iteration":633,"passed_time":0.4173286328,"remaining_time":0.2409184221},
{"learn":[3.630301009],"iteration":634,"passed_time":0.4178312075,"remaining_time":0.2401706941},
{"learn":[3.629077964],"iteration":635,"passed_time":0.4183149094,"remaining_time":0.2394129356},
{"learn":[3.628004522],"iteration":636,"passed_time":0.4188880559,"remaining_time":0.2387070083},
{"learn":[3.625062876],"iteration":637,"passed_time":0.4194539718,"remaining_time":0.2379973946},
{"learn":[3.624917986],"iteration":638,"passed_time":0.4199534894,"remaining_time":0.2372507194},
{"learn":[3.622887087],"iteration":639,"passed_time":0.4204813627,"remaining_time":0.2365207665},
{"learn":[3.621220865],"iteration":640,"passed_time":0.4211069512,"remaining_time":0.2358461708},
{"learn":[3.621143844],"iteration":641,"passed_time":0.4216067727,"remaining_time":0.235101596},
{"learn":[3.620822821],"iteration":642,"passed_time":0.4221384577,"remaining_time":0.2343754734},
{"learn":[3.619202826],"iteration":643,"passed_time":0.4227071699,"remaining_time":0.2336704231},
{"learn":[3.618204882],"iteration":644,"passed_time":0.4232716816,"remaining_time":0.2329634837},
{"learn":[3.614259666],"iteration":645,"passed_time":0.4238350337,"remaining_time":0.2322563498},
{"learn":[3.613415661],"iteration":646,"passed_time":0.4244061156,"remaining_time":0.2315538776},
{"learn":[3.611096773],"iteration":647,"passed_time":0.4248881509,"remaining_time":0.23080344},
{"learn":[3.610820695],"iteration":648,"passed_time":0.425361293,"remaining_time":0.2300490198},
{"learn":[3.609290065],"iteration":649,"passed_time":0.4258129535,"remaining_time":0.229283898},
{"learn":[3.60897947],"iteration":650,"passed_time":0.4263078057,"remaining_time":0.2285428943},
{"learn":[3.606570702],"iteration":651,"passed_time":0.4268910294,"remaining_time":0.2278498132},
{"learn":[3.606292637],"iteration":652,"passed_time":0.4274436036,"remaining_time":0.2271407817},
{"learn":[3.602753838],"iteration":653,"passed_time":0.4280656846,"remaining_time":0.2264690013},
{"learn":[3.599755869],"iteration":654,"passed_time":0.4287285582,"remaining_time":0.2258188589},
{"learn":[3.599509575],"iteration":655,"passed_time":0.4292629071,"remaining_time":0.2251012806},
{"learn":[3.595337722],"iteration":656,"passed_time":0.429749896,"remaining_time":0.2243595348},
{"learn":[3.595168561],"iteration":657,"passed_time":0.4302764207,"remaining_time":0.2236391123},
{"learn":[3.59290559],"iteration":658,"passed_time":0.4307886574,"remaining_time":0.2229118849},
{"learn":[3.592015928],"iteration":659,"passed_time":0.4312778896,"remaining_time":0.2221734583},
{"learn":[3.590680403],"iteration":660,"passed_time":0.4318169152,"remaining_time":0.2214613226},
{"learn":[3.590361532],"iteration":661,"passed_time":0.4323201289,"remaining_time":0.2207314253},
{"learn":[3.589069739],"iteration":662,"passed_time":0.4327994482,"remaining_time":0.2199900664},
{"learn":[3.585010186],"iteration":663,"passed_time":0.4333160717,"remaining_time":0.2192683736},
{"learn":[3.582997552],"iteration":664,"passed_time":0.4339851741,"remaining_time":0.2186241102},
{"learn":[3.582119256],"iteration":665,"passed_time":0.4345293159,"remaining_time":0.2179171044},
{"learn":[3.579019356],"iteration":666,"passed_time":0.4351916778,"remaining_time":0.2172696083},
{"learn":[3.57719559],"iteration":667,"passed_time":0.435784766,"remaining_time":0.2165876382},
{"learn":[3.574050046],"iteration":668,"passed_time":0.4363879023,"remaining_time":0.2159109053},
{"learn":[3.572204518],"iteration":669,"passed_time":0.4368912921,"remaining_time":0.2151852633},
{"learn":[3.569508025],"iteration":670,"passed_time":0.437371769,"remaining_time":0.2144490492},
{"learn":[3.566268704],"iteration":671,"passed_time":0.4379415022,"remaining_time":0.2137571618},
{"learn":[3.562564052],"iteration":672,"passed_time":0.4384830493,"remaining_time":0.2130519423},
{"learn":[3.561173586],"iteration":673,"passed_time":0.4390497956,"remaining_time":0.2123593967},
{"learn":[3.559551904],"iteration":674,"passed_time":0.4396332796,"remaining_time":0.2116752828},
{"learn":[3.558593054],"iteration":675,"passed_time":0.4401753644,"remaining_time":0.2109716244},
{"learn":[3.555647008],"iteration":676,"passed_time":0.4407657978,"remaining_time":0.2102915106},
{"learn":[3.553100059],"iteration":677,"passed_time":0.4412666247,"remaining_time":0.2095691049},
{"learn":[3.55085578],"iteration":678,"passed_time":0.4418367839,"remaining_time":0.208880129},
{"learn":[3.550737965],"iteration":679,"passed_time":0.4424139246,"remaining_time":0.2081947881},
{"learn":[3.549408772],"iteration":680,"passed_time":0.443012059,"remaining_time":0.2075195989},
{"learn":[3.547390589],"iteration":681,"passed_time":0.4436312679,"remaining_time":0.2068544622},
{"learn":[3.54723575],"iteration":682,"passed_time":0.4441917842,"remaining_time":0.206162219},
{"learn":[3.543988891],"iteration":683,"passed_time":0.4447888597,"remaining_time":0.205487251},
{"learn":[3.543868508],"iteration":684,"passed_time":0.4452802841,"remaining_time":0.2047639263},
{"learn":[3.542752124],"iteration":685,"passed_time":0.4457956581,"remaining_time":0.20405224},
{"learn":[3.541334315],"iteration":686,"passed_time":0.4463400169,"remaining_time":0.2033543308},
{"learn":[3.540208266],"iteration":687,"passed_time":0.4468391393,"remaining_time":0.2026363538},
{"learn":[3.537730983],"iteration":688,"passed_time":0.447370693,"remaining_time":0.201933651},
{"learn":[3.53419867],"iteration":689,"passed_time":0.4479102761,"remaining_time":0.2012350516},
{"learn":[3.532628335],"iteration":690,"passed_time":0.4484288246,"remaining_time":0.2005275062},
{"learn":[3.532204987],"iteration":691,"passed_time":0.4489878101,"remaining_time":0.1998385051},
{"learn":[3.530618147],"iteration":692,"passed_time":0.4495502924,"remaining_time":0.1991514282},
{"learn":[3.528909306],"iteration":693,"passed_time":0.4500650066,"remaining_time":0.1984436485},
{"learn":[3.526700678],"iteration":694,"passed_time":0.4505917093,"remaining_time":0.1977416854},
{"learn":[3.526439574],"iteration":695,"passed_time":0.4511037676,"remaining_time":0.1970338295},
{"learn":[3.525784216],"iteration":696,"passed_time":0.4516366726,"remaining_time":0.196335598},
{"learn":[3.524112693],"iteration":697,"passed_time":0.4521724307,"remaining_time":0.1956390746},
{"learn":[3.522813541],"iteration":698,"passed_time":0.4527264679,"remaining_time":0.1949508825},
{"learn":[3.519148203],"iteration":699,"passed_time":0.4532588077,"remaining_time":0.1942537747},
{"learn":[3.517236747],"iteration":700,"passed_time":0.4538187228,"remaining_time":0.1935688989},
{"learn":[3.515603888],"iteration":701,"passed_time":0.4544300971,"remaining_time":0.1929062235},
{"learn":[3.51263524],"iteration":702,"passed_time":0.4550898394,"remaining_time":0.1922641285},
{"learn":[3.51123442],"iteration":703,"passed_time":0.4556276973,"remaining_time":0.1915707364},
{"learn":[3.50828027],"iteration":704,"passed_time":0.4562006697,"remaining_time":0.1908924788},
{"learn":[3.508265537],"iteration":705,"passed_time":0.4565372314,"remaining_time":0.1901160709},
{"learn":[3.506774876],"iteration":706,"passed_time":0.4571804852,"remaining_time":0.1894680087},
{"learn":[3.50552068],"iteration":707,"passed_time":0.4577877692,"remaining_time":0.1888051251},
{"learn":[3.501973993],"iteration":708,"passed_time":0.4583566015,"remaining_time":0.1881266164},
{"learn":[3.498880354],"iteration":709,"passed_time":0.458897257,"remaining_time":0.1874369078},
{"learn":[3.497370959],"iteration":710,"passed_time":0.4594793548,"remaining_time":0.1867644635},
{"learn":[3.496050455],"iteration":711,"passed_time":0.4599798951,"remaining_time":0.1860592834},
{"learn":[3.495630067],"iteration":712,"passed_time":0.4605285864,"remaining_time":0.1853740593},
{"learn":[3.49550669],"iteration":713,"passed_time":0.461071122,"remaining_time":0.184686752},
{"learn":[3.493652375],"iteration":714,"passed_time":0.4617191664,"remaining_time":0.1840419055},
{"learn":[3.491915684],"iteration":715,"passed_time":0.4623015345,"remaining_time":0.1833709997},
{"learn":[3.490303956],"iteration":716,"passed_time":0.4628258877,"remaining_time":0.1826774424},
{"learn":[3.488363853],"iteration":717,"passed_time":0.4634384154,"remaining_time":0.1820189877},
{"learn":[3.485483936],"iteration":718,"passed_time":0.4639925878,"remaining_time":0.1813378542},
{"learn":[3.483763466],"iteration":719,"passed_time":0.4646867309,"remaining_time":0.1807115064},
{"learn":[3.481642352],"iteration":720,"passed_time":0.4652358811,"remaining_time":0.1800288638},
{"learn":[3.479826119],"iteration":721,"passed_time":0.4658823606,"remaining_time":0.1793840668},
{"learn":[3.478588728],"iteration":722,"passed_time":0.4664184914,"remaining_time":0.1786969877},
{"learn":[3.475390887],"iteration":723,"passed_time":0.4670443274,"remaining_time":0.1780445226},
{"learn":[3.472636852],"iteration":724,"passed_time":0.4676354114,"remaining_time":0.1773789492},
{"learn":[3.47061883],"iteration":725,"passed_time":0.4681260214,"remaining_time":0.176675661},
{"learn":[3.46953149],"iteration":726,"passed_time":0.4686587033,"remaining_time":0.1759887565},
{"learn":[3.467217162],"iteration":727,"passed_time":0.4691698573,"remaining_time":0.1752942324},
{"learn":[3.465686216],"iteration":728,"passed_time":0.4696545129,"remaining_time":0.1745903608},
{"learn":[3.462631216],"iteration":729,"passed_time":0.4701856281,"remaining_time":0.1739042734},
{"learn":[3.461451053],"iteration":730,"passed_time":0.4706865709,"remaining_time":0.1732075069},
{"learn":[3.458950469],"iteration":731,"passed_time":0.4714460406,"remaining_time":0.1726059274},
{"learn":[3.458072145],"iteration":732,"passed_time":0.4721021266,"remaining_time":0.1719662589},
{"learn":[3.454364268],"iteration":733,"passed_time":0.4726212691,"remaining_time":0.1712769177},
{"learn":[3.453243406],"iteration":734,"passed_time":0.4731942847,"remaining_time":0.1706074632},
{"learn":[3.453017963],"iteration":735,"passed_time":0.4736897228,"remaining_time":0.1699104441},
{"learn":[3.45201581],"iteration":736,"passed_time":0.4742318157,"remaining_time":0.1692306208},
{"learn":[3.449510107],"iteration":737,"passed_time":0.4748316937,"remaining_time":0.1685716853},
{"learn":[3.447189189],"iteration":738,"passed_time":0.4753169627,"remaining_time":0.167872432},
{"learn":[3.446423605],"iteration":739,"passed_time":0.4757653879,"remaining_time":0.167160812},
{"learn":[3.445531987],"iteration":740,"passed_time":0.4762210254,"remaining_time":0.1664524232},
{"learn":[3.445328199],"iteration":741,"passed_time":0.4767251595,"remaining_time":0.1657615784},
{"learn":[3.443327544],"iteration":742,"passed_time":0.4772694958,"remaining_time":0.1650851419},
{"learn":[3.441475798],"iteration":743,"passed_time":0.4778382271,"remaining_time":0.1644174545},
{"learn":[3.439046501],"iteration":744,"passed_time":0.478407839,"remaining_time":0.1637503342},
{"learn":[3.435899469],"iteration":745,"passed_time":0.4789060157,"remaining_time":0.1630591528},
{"learn":[3.433988352],"iteration":746,"passed_time":0.4795139319,"remaining_time":0.1624056557},
{"learn":[3.433413263],"iteration":747,"passed_time":0.4799942068,"remaining_time":0.1617092782},
{"learn":[3.429944699],"iteration":748,"passed_time":0.4805485123,"remaining_time":0.1610382865},
{"learn":[3.429291634],"iteration":749,"passed_time":0.4810713715,"remaining_time":0.1603571238},
{"learn":[3.429175603],"iteration":750,"passed_time":0.4815736783,"remaining_time":0.1596695684},
{"learn":[3.428780323],"iteration":751,"passed_time":0.4820513592,"remaining_time":0.1589743844},
{"learn":[3.423893341],"iteration":752,"passed_time":0.4825351633,"remaining_time":0.1582817866},
{"learn":[3.421024316],"iteration":753,"passed_time":0.4830950715,"remaining_time":0.1576145724},
{"learn":[3.420969872],"iteration":754,"passed_time":0.4835874319,"remaining_time":0.1569257229},
{"learn":[3.419544785],"iteration":755,"passed_time":0.4841544867,"remaining_time":0.156261501},
{"learn":[3.417057977],"iteration":756,"passed_time":0.4846715403,"remaining_time":0.1555814852},
{"learn":[3.415160245],"iteration":757,"passed_time":0.4852037072,"remaining_time":0.1549067244},
{"learn":[3.412854597],"iteration":758,"passed_time":0.4857593464,"remaining_time":0.1542397925},
{"learn":[3.410926347],"iteration":759,"passed_time":0.4863043745,"remaining_time":0.1535698025},
{"learn":[3.408963843],"iteration":760,"passed_time":0.4869374627,"remaining_time":0.1529277971},
{"learn":[3.407629634],"iteration":761,"passed_time":0.4874049845,"remaining_time":0.1522341028},
{"learn":[3.404384724],"iteration":762,"passed_time":0.4880018564,"remaining_time":0.1515811795},
{"learn":[3.403041656],"iteration":763,"passed_time":0.4885002256,"remaining_time":0.1508979754},
{"learn":[3.401101731],"iteration":764,"passed_time":0.4890741651,"remaining_time":0.150238469},
{"learn":[3.400890668],"iteration":765,"passed_time":0.4896164895,"remaining_time":0.1495695281},
{"learn":[3.399289941],"iteration":766,"passed_time":0.4901173519,"remaining_time":0.148888322},
{"learn":[3.399202366],"iteration":767,"passed_time":0.4906191436,"remaining_time":0.1482078663},
{"learn":[3.397447845],"iteration":768,"passed_time":0.4910917767,"remaining_time":0.1475191163},
{"learn":[3.394655341],"iteration":769,"passed_time":0.4915913415,"remaining_time":0.1468389721},
{"learn":[3.393228229],"iteration":770,"passed_time":0.4921069405,"remaining_time":0.1461640589},
{"learn":[3.389691197],"iteration":771,"passed_time":0.4925856543,"remaining_time":0.1454786647},
{"learn":[3.389626772],"iteration":772,"passed_time":0.4930936736,"remaining_time":0.1448024113},
{"learn":[3.388480222],"iteration":773,"passed_time":0.4936305109,"remaining_time":0.1441350071},
{"learn":[3.388215066],"iteration":774,"passed_time":0.494225906,"remaining_time":0.1434849404},
{"learn":[3.386324358],"iteration":775,"passed_time":0.4948823246,"remaining_time":0.1428526298},
{"learn":[3.383913061],"iteration":776,"passed_time":0.4953975444,"remaining_time":0.1421797328},
{"learn":[3.382839768],"iteration":777,"passed_time":0.4958815015,"remaining_time":0.1414983205},
{"learn":[3.381961844],"iteration":778,"passed_time":0.496437042,"remaining_time":0.1408377231},
{"learn":[3.381521703],"iteration":779,"passed_time":0.496964621,"remaining_time":0.1401695085},
{"learn":[3.380918963],"iteration":780,"passed_time":0.4974662948,"remaining_time":0.13949439},
{"learn":[3.377139006],"iteration":781,"passed_time":0.4979992324,"remaining_time":0.1388284305},
{"learn":[3.376004372],"iteration":782,"passed_time":0.4984666061,"remaining_time":0.1381446405},
{"learn":[3.373826468],"iteration":783,"passed_time":0.4989969015,"remaining_time":0.1374787382},
{"learn":[3.373546786],"iteration":784,"passed_time":0.4995245575,"remaining_time":0.1368124584},
{"learn":[3.372109181],"iteration":785,"passed_time":0.5000835927,"remaining_time":0.1361550749},
{"learn":[3.370764924],"iteration":786,"passed_time":0.500563101,"remaining_time":0.1354764174},
{"learn":[3.367833107],"iteration":787,"passed_time":0.5011932562,"remaining_time":0.1348387948},
{"learn":[3.36450404],"iteration":788,"passed_time":0.5016613796,"remaining_time":0.1341578594},
{"learn":[3.361794558],"iteration":789,"passed_time":0.5022607195,"remaining_time":0.1335123432},
{"learn":[3.356880529],"iteration":790,"passed_time":0.5028397057,"remaining_time":0.1328615657},
{"learn":[3.353843509],"iteration":791,"passed_time":0.5033905416,"remaining_time":0.1322035766},
{"learn":[3.353640253],"iteration":792,"passed_time":0.5039136106,"remaining_time":0.1315386096},
{"learn":[3.353055088],"iteration":793,"passed_time":0.5044244485,"remaining_time":0.1308708267},
{"learn":[3.351415617],"iteration":794,"passed_time":0.504876342,"remaining_time":0.1301882391},
{"learn":[3.349169061],"iteration":795,"passed_time":0.5054402617,"remaining_time":0.1295349414},
{"learn":[3.346211014],"iteration":796,"passed_time":0.5059430001,"remaining_time":0.1288662849},
{"learn":[3.344560452],"iteration":797,"passed_time":0.5064936474,"remaining_time":0.1282101714},
{"learn":[3.344445461],"iteration":798,"passed_time":0.507005682,"remaining_time":0.1275446084},
{"learn":[3.342608898],"iteration":799,"passed_time":0.5075083241,"remaining_time":0.126877081},
{"learn":[3.339572899],"iteration":800,"passed_time":0.5080544992,"remaining_time":0.1262207807},
{"learn":[3.339309302],"iteration":801,"passed_time":0.508543087,"remaining_time":0.1255505377},
{"learn":[3.33698088],"iteration":802,"passed_time":0.5090485292,"remaining_time":0.124884882},
{"learn":[3.334746342],"iteration":803,"passed_time":0.5097021598,"remaining_time":0.1242557504},
{"learn":[3.332048511],"iteration":804,"passed_time":0.5102804835,"remaining_time":0.1236083159},
{"learn":[3.331932544],"iteration":805,"passed_time":0.5107727835,"remaining_time":0.1229403474},
{"learn":[3.330541133],"iteration":806,"passed_time":0.5112689051,"remaining_time":0.1222737282},
{"learn":[3.329124989],"iteration":807,"passed_time":0.5117979812,"remaining_time":0.1216153619},
{"learn":[3.32583918],"iteration":808,"passed_time":0.5123509048,"remaining_time":0.1209629454},
{"learn":[3.325287299],"iteration":809,"passed_time":0.5128062963,"remaining_time":0.1202878967},
{"learn":[3.322745162],"iteration":810,"passed_time":0.5133410777,"remaining_time":0.1196318911},
{"learn":[3.319733662],"iteration":811,"passed_time":0.5138436095,"remaining_time":0.1189687175},
{"learn":[3.318080007],"iteration":812,"passed_time":0.5143447008,"remaining_time":0.1183056077},
{"learn":[3.317179538],"iteration":813,"passed_time":0.5148577105,"remaining_time":0.1176456194},
{"learn":[3.315685949],"iteration":814,"passed_time":0.5154083949,"remaining_time":0.1169945436},
{"learn":[3.314944576],"iteration":815,"passed_time":0.5159210384,"remaining_time":0.1163351361},
{"learn":[3.312369052],"iteration":816,"passed_time":0.5165006544,"remaining_time":0.1156910891},
{"learn":[3.312321621],"iteration":817,"passed_time":0.5168915635,"remaining_time":0.1150052134},
{"learn":[3.309465776],"iteration":818,"passed_time":0.5174276767,"remaining_time":0.1143521483},
{"learn":[3.308307377],"iteration":819,"passed_time":0.5179503047,"remaining_time":0.1136964084},
{"learn":[3.308076804],"iteration":820,"passed_time":0.5184498442,"remaining_time":0.1130359587},
{"learn":[3.305643326],"iteration":821,"passed_time":0.5190090483,"remaining_time":0.1123888207},
{"learn":[3.304154814],"iteration":822,"passed_time":0.5195319542,"remaining_time":0.1117340898},
{"learn":[3.303076321],"iteration":823,"passed_time":0.520040913,"remaining_time":0.1110766999},
{"learn":[3.301746372],"iteration":824,"passed_time":0.5206082651,"remaining_time":0.1104320562},
{"learn":[3.301345455],"iteration":825,"passed_time":0.5211387048,"remaining_time":0.109779824},
{"learn":[3.299181039],"iteration":826,"passed_time":0.5216573425,"remaining_time":0.1091254175},
{"learn":[3.297989357],"iteration":827,"passed_time":0.5221124335,"remaining_time":0.1084581384},
{"learn":[3.294775182],"iteration":828,"passed_time":0.5225871263,"remaining_time":0.1077954145},
{"learn":[3.293840636],"iteration":829,"passed_time":0.5230444377,"remaining_time":0.1071295836},
{"learn":[3.289279397],"iteration":830,"passed_time":0.5235895205,"remaining_time":0.1064821047},
{"learn":[3.286204979],"iteration":831,"passed_time":0.5241361882,"remaining_time":0.1058351918},
{"learn":[3.284833593],"iteration":832,"passed_time":0.5247139684,"remaining_time":0.1051947572},
{"learn":[3.283519914],"iteration":833,"passed_time":0.5252790144,"remaining_time":0.1045519381},
{"learn":[3.282853026],"iteration":834,"passed_time":0.5257922391,"remaining_time":0.1038990652},
{"learn":[3.281944673],"iteration":835,"passed_time":0.5263260527,"remaining_time":0.1032505654},
{"learn":[3.279764865],"iteration":836,"passed_time":0.5268536275,"remaining_time":0.1026011246},
{"learn":[3.277468839],"iteration":837,"passed_time":0.5273320237,"remaining_time":0.1019424676},
{"learn":[3.277124974],"iteration":838,"passed_time":0.5278085075,"remaining_time":0.1012838733},
{"learn":[3.275636037],"iteration":839,"passed_time":0.5283636133,"remaining_time":0.1006406882},
{"learn":[3.274413635],"iteration":840,"passed_time":0.5289068217,"remaining_time":0.09999546332},
{"learn":[3.272636087],"iteration":841,"passed_time":0.5293401915,"remaining_time":0.09932986966},
{"learn":[3.269644466],"iteration":842,"passed_time":0.529987653,"remaining_time":0.09870469932},
{"learn":[3.26852083],"iteration":843,"passed_time":0.5305230414,"remaining_time":0.09805876121},
{"learn":[3.267820927],"iteration":844,"passed_time":0.5310345326,"remaining_time":0.09740870124},
{"learn":[3.267331099],"iteration":845,"passed_time":0.531569487,"remaining_time":0.09676323994},
{"learn":[3.267231014],"iteration":846,"passed_time":0.5320773218,"remaining_time":0.09611314078},
{"learn":[3.267158695],"iteration":847,"passed_time":0.5325736803,"remaining_time":0.09546132006},
{"learn":[3.264718705],"iteration":848,"passed_time":0.533077276,"remaining_time":0.09481115274},
{"learn":[3.261678512],"iteration":849,"passed_time":0.5335876646,"remaining_time":0.09416252905},
{"learn":[3.261368381],"iteration":850,"passed_time":0.5340712199,"remaining_time":0.09350953205},
{"learn":[3.260128799],"iteration":851,"passed_time":0.5345681039,"remaining_time":0.09285924809},
{"learn":[3.258972952],"iteration":852,"passed_time":0.5350811423,"remaining_time":0.09221210776},
{"learn":[3.258724846],"iteration":853,"passed_time":0.535574688,"remaining_time":0.091561949},
{"learn":[3.25686724],"iteration":854,"passed_time":0.5360430107,"remaining_time":0.09090787902},
{"learn":[3.255750259],"iteration":855,"passed_time":0.5365193105,"remaining_time":0.09025558494},
{"learn":[3.254915866],"iteration":856,"passed_time":0.5370482971,"remaining_time":0.08961249298},
{"learn":[3.254348625],"iteration":857,"passed_time":0.5374879217,"remaining_time":0.08895487749},
{"learn":[3.253408514],"iteration":858,"passed_time":0.5379523995,"remaining_time":0.08830184905},
{"learn":[3.253291714],"iteration":859,"passed_time":0.5386347169,"remaining_time":0.08768472135},
{"learn":[3.250186342],"iteration":860,"passed_time":0.5392233474,"remaining_time":0.0870523174},
{"learn":[3.249141318],"iteration":861,"passed_time":0.5398224447,"remaining_time":0.08642169068},
{"learn":[3.246300388],"iteration":862,"passed_time":0.5403508492,"remaining_time":0.08577991464},
{"learn":[3.245205135],"iteration":863,"passed_time":0.5409358314,"remaining_time":0.08514730679},
{"learn":[3.244403535],"iteration":864,"passed_time":0.5415798318,"remaining_time":0.08452402},
{"learn":[3.244211781],"iteration":865,"passed_time":0.542309151,"remaining_time":0.08391388711},
{"learn":[3.242286347],"iteration":866,"passed_time":0.5429509038,"remaining_time":0.08329004638},
{"learn":[3.239606746],"iteration":867,"passed_time":0.5434063737,"remaining_time":0.08263783563},
{"learn":[3.236773361],"iteration":868,"passed_time":0.5439641404,"remaining_time":0.08200149872},
{"learn":[3.234552446],"iteration":869,"passed_time":0.5445101888,"remaining_time":0.08136359143},
{"learn":[3.233724647],"iteration":870,"passed_time":0.5450817662,"remaining_time":0.08072967606},
{"learn":[3.230851485],"iteration":871,"passed_time":0.5456009948,"remaining_time":0.08008821942},
{"learn":[3.227728941],"iteration":872,"passed_time":0.5461720028,"remaining_time":0.07945457544},
{"learn":[3.225787575],"iteration":873,"passed_time":0.5467670217,"remaining_time":0.07882453631},
{"learn":[3.222797487],"iteration":874,"passed_time":0.5473264309,"remaining_time":0.07818949012},
{"learn":[3.22137014],"iteration":875,"passed_time":0.5478747881,"remaining_time":0.0775530522},
{"learn":[3.219701963],"iteration":876,"passed_time":0.5484550628,"remaining_time":0.07692129159},
{"learn":[3.21783327],"iteration":877,"passed_time":0.5490401032,"remaining_time":0.07629031046},
{"learn":[3.217713355],"iteration":878,"passed_time":0.5495041807,"remaining_time":0.07564278255},
{"learn":[3.217666091],"iteration":879,"passed_time":0.5500365507,"remaining_time":0.07500498419},
{"learn":[3.214962005],"iteration":880,"passed_time":0.5505132894,"remaining_time":0.07435991083},
{"learn":[3.214081828],"iteration":881,"passed_time":0.5510319592,"remaining_time":0.07372082901},
{"learn":[3.213358337],"iteration":882,"passed_time":0.5515302305,"remaining_time":0.07307931706},
{"learn":[3.210850401],"iteration":883,"passed_time":0.552043557,"remaining_time":0.07244010477},
{"learn":[3.207810328],"iteration":884,"passed_time":0.5525585786,"remaining_time":0.07180139722},
{"learn":[3.204935073],"iteration":885,"passed_time":0.553105875,"remaining_time":0.07116712161},
{"learn":[3.20280198],"iteration":886,"passed_time":0.5536372523,"remaining_time":0.0705310141},
{"learn":[3.200663495],"iteration":887,"passed_time":0.5542249582,"remaining_time":0.06990224698},
{"learn":[3.197301669],"iteration":888,"passed_time":0.5547334272,"remaining_time":0.06926367876},
{"learn":[3.195666943],"iteration":889,"passed_time":0.555213986,"remaining_time":0.06862195332},
{"learn":[3.193886506],"iteration":890,"passed_time":0.5557521202,"remaining_time":0.06798763311},
{"learn":[3.190601248],"iteration":891,"passed_time":0.556286897,"remaining_time":0.06735312206},
{"learn":[3.188983797],"iteration":892,"passed_time":0.5567411001,"remaining_time":0.06670917997},
{"learn":[3.187365749],"iteration":893,"passed_time":0.5572841275,"remaining_time":0.06607619409},
{"learn":[3.186160771],"iteration":894,"passed_time":0.5578278094,"remaining_time":0.06544348601},
{"learn":[3.185358981],"iteration":895,"passed_time":0.5583718417,"remaining_time":0.06481101734},
{"learn":[3.183832164],"iteration":896,"passed_time":0.5588979757,"remaining_time":0.06417669063},
{"learn":[3.183106966],"iteration":897,"passed_time":0.5594127366,"remaining_time":0.06354131307},
{"learn":[3.182838152],"iteration":898,"passed_time":0.5599367921,"remaining_time":0.06290724806},
{"learn":[3.180835453],"iteration":899,"passed_time":0.5604424426,"remaining_time":0.06227138251},
{"learn":[3.179957348],"iteration":900,"passed_time":0.5610035536,"remaining_time":0.0616418999},
{"learn":[3.179752966],"iteration":901,"passed_time":0.5615433763,"remaining_time":0.06101025596},
{"learn":[3.178851983],"iteration":902,"passed_time":0.5620788684,"remaining_time":0.0603783502},
{"learn":[3.176748586],"iteration":903,"passed_time":0.5627432624,"remaining_time":0.05976034645},
{"learn":[3.172960988],"iteration":904,"passed_time":0.5633002055,"remaining_time":0.0591309608},
{"learn":[3.172794225],"iteration":905,"passed_time":0.5638578034,"remaining_time":0.058501803},
{"learn":[3.169996507],"iteration":906,"passed_time":0.5643697935,"remaining_time":0.05786812657},
{"learn":[3.16813015],"iteration":907,"passed_time":0.5648417501,"remaining_time":0.0572306619},
{"learn":[3.166920871],"iteration":908,"passed_time":0.5653531482,"remaining_time":0.05659750989},
{"learn":[3.16531606],"iteration":909,"passed_time":0.5657767049,"remaining_time":0.05595593785},
{"learn":[3.162035247],"iteration":910,"passed_time":0.5662453028,"remaining_time":0.05531924473},
{"learn":[3.16189467],"iteration":911,"passed_time":0.566751977,"remaining_time":0.05468659427},
{"learn":[3.161008416],"iteration":912,"passed_time":0.5673033001,"remaining_time":0.05405847438},
{"learn":[3.160560787],"iteration":913,"passed_time":0.5678121977,"remaining_time":0.05342653064},
{"learn":[3.160416261],"iteration":914,"passed_time":0.5683533966,"remaining_time":0.05279785651},
{"learn":[3.15844291],"iteration":915,"passed_time":0.5689387898,"remaining_time":0.05217342614},
{"learn":[3.155040501],"iteration":916,"passed_time":0.5695664089,"remaining_time":0.05155290288},
{"learn":[3.154937548],"iteration":917,"passed_time":0.5701773063,"remaining_time":0.0509308705},
{"learn":[3.153721161],"iteration":918,"passed_time":0.5707166793,"remaining_time":0.05030255824},
{"learn":[3.153170511],"iteration":919,"passed_time":0.5711902236,"remaining_time":0.0496687151},
{"learn":[3.153113601],"iteration":920,"passed_time":0.5716476024,"remaining_time":0.04903383343},
{"learn":[3.150607379],"iteration":921,"passed_time":0.5722115309,"remaining_time":0.04840835077},
{"learn":[3.148408359],"iteration":922,"passed_time":0.5727298341,"remaining_time":0.04777919526},
{"learn":[3.147495728],"iteration":923,"passed_time":0.5732288852,"remaining_time":0.04714869619},
{"learn":[3.146946235],"iteration":924,"passed_time":0.573784327,"remaining_time":0.04652305354},
{"learn":[3.14472738],"iteration":925,"passed_time":0.5742537014,"remaining_time":0.04589068456},
{"learn":[3.144469477],"iteration":926,"passed_time":0.574757384,"remaining_time":0.04526136897},
{"learn":[3.142975516],"iteration":927,"passed_time":0.5752073036,"remaining_time":0.04462815287},
{"learn":[3.14079113],"iteration":928,"passed_time":0.5756800691,"remaining_time":0.0439970774},
{"learn":[3.138173032],"iteration":929,"passed_time":0.5762152321,"remaining_time":0.04337103897},
{"learn":[3.136352813],"iteration":930,"passed_time":0.5767692445,"remaining_time":0.04274659277},
{"learn":[3.133735004],"iteration":931,"passed_time":0.5773734561,"remaining_time":0.04212596032},
{"learn":[3.1319496],"iteration":932,"passed_time":0.5778478849,"remaining_time":0.04149604318},
{"learn":[3.129865343],"iteration":933,"passed_time":0.5783818687,"remaining_time":0.04087066738},
{"learn":[3.129830206],"iteration":934,"passed_time":0.5788484104,"remaining_time":0.04024079859},
{"learn":[3.126676562],"iteration":935,"passed_time":0.5794239936,"remaining_time":0.03961873461},
{"learn":[3.12645665],"iteration":936,"passed_time":0.5798862392,"remaining_time":0.03898914948},
{"learn":[3.126378007],"iteration":937,"passed_time":0.5803543878,"remaining_time":0.03836031135},
{"learn":[3.124621914],"iteration":938,"passed_time":0.5809397726,"remaining_time":0.03773943145},
{"learn":[3.123379018],"iteration":939,"passed_time":0.5814676494,"remaining_time":0.03711495635},
{"learn":[3.123332451],"iteration":940,"passed_time":0.5819893521,"remaining_time":0.03649029944},
{"learn":[3.122432444],"iteration":941,"passed_time":0.5826929834,"remaining_time":0.03587706267},
{"learn":[3.121889006],"iteration":942,"passed_time":0.5833150947,"remaining_time":0.03525870668},
{"learn":[3.121070914],"iteration":943,"passed_time":0.584032476,"remaining_time":0.03464599434},
{"learn":[3.118444705],"iteration":944,"passed_time":0.5846461066,"remaining_time":0.03402702208},
{"learn":[3.116820458],"iteration":945,"passed_time":0.5851544045,"remaining_time":0.03340204846},
{"learn":[3.114971041],"iteration":946,"passed_time":0.5857313853,"remaining_time":0.03278116517},
{"learn":[3.114685138],"iteration":947,"passed_time":0.5863389088,"remaining_time":0.03216204985},
{"learn":[3.113399363],"iteration":948,"passed_time":0.5868484942,"remaining_time":0.03153769568},
{"learn":[3.110575399],"iteration":949,"passed_time":0.5873529961,"remaining_time":0.03091331558},
{"learn":[3.110466553],"iteration":950,"passed_time":0.5878261845,"remaining_time":0.03028757418},
{"learn":[3.108691641],"iteration":951,"passed_time":0.5884649642,"remaining_time":0.02967050239},
{"learn":[3.107898017],"iteration":952,"passed_time":0.5890239539,"remaining_time":0.02904944998},
{"learn":[3.105551729],"iteration":953,"passed_time":0.589567196,"remaining_time":0.02842776836},
{"learn":[3.104824945],"iteration":954,"passed_time":0.5901013318,"remaining_time":0.02780582192},
{"learn":[3.103186704],"iteration":955,"passed_time":0.5907154577,"remaining_time":0.02718774073},
{"learn":[3.102330655],"iteration":956,"passed_time":0.5914911159,"remaining_time":0.02657692579},
{"learn":[3.102291298],"iteration":957,"passed_time":0.5920236799,"remaining_time":0.02595510914},
{"learn":[3.100363529],"iteration":958,"passed_time":0.592523609,"remaining_time":0.02533208339},
{"learn":[3.097871596],"iteration":959,"passed_time":0.5930940824,"remaining_time":0.02471225343},
{"learn":[3.097372213],"iteration":960,"passed_time":0.5937054436,"remaining_time":0.02409418554},
{"learn":[3.095981813],"iteration":961,"passed_time":0.5942884067,"remaining_time":0.02347500983},
{"learn":[3.095347452],"iteration":962,"passed_time":0.5948429587,"remaining_time":0.02285481773},
{"learn":[3.094728409],"iteration":963,"passed_time":0.5953476543,"remaining_time":0.02223289995},
{"learn":[3.094118537],"iteration":964,"passed_time":0.5958053239,"remaining_time":0.02160951952},
{"learn":[3.093793695],"iteration":965,"passed_time":0.5962957196,"remaining_time":0.02098763402},
{"learn":[3.092581602],"iteration":966,"passed_time":0.5968081499,"remaining_time":0.02036677244},
{"learn":[3.091694202],"iteration":967,"passed_time":0.5973894536,"remaining_time":0.01974841169},
{"learn":[3.090298312],"iteration":968,"passed_time":0.5979768916,"remaining_time":0.01913032367},
{"learn":[3.090020107],"iteration":969,"passed_time":0.5986061926,"remaining_time":0.01851359359},
{"learn":[3.088949869],"iteration":970,"passed_time":0.5990969775,"remaining_time":0.01789270067},
{"learn":[3.086700204],"iteration":971,"passed_time":0.5996463202,"remaining_time":0.01727376231},
{"learn":[3.086584317],"iteration":972,"passed_time":0.600222653,"remaining_time":0.01665571596},
{"learn":[3.084850742],"iteration":973,"passed_time":0.6008149456,"remaining_time":0.0160381813},
{"learn":[3.084239948],"iteration":974,"passed_time":0.6014130375,"remaining_time":0.01542084712},
{"learn":[3.082561673],"iteration":975,"passed_time":0.6020218175,"remaining_time":0.01480381518},
{"learn":[3.07991814],"iteration":976,"passed_time":0.6025381459,"remaining_time":0.0141846237},
{"learn":[3.079350277],"iteration":977,"passed_time":0.6030799028,"remaining_time":0.01356621458},
{"learn":[3.077637462],"iteration":978,"passed_time":0.603587813,"remaining_time":0.01294723603},
{"learn":[3.076733301],"iteration":979,"passed_time":0.6041278225,"remaining_time":0.01232913923},
{"learn":[3.07594065],"iteration":980,"passed_time":0.6046531225,"remaining_time":0.01171091675},
{"learn":[3.072594655],"iteration":981,"passed_time":0.6051743599,"remaining_time":0.01109280904},
{"learn":[3.071977674],"iteration":982,"passed_time":0.6056720367,"remaining_time":0.01047449097},
{"learn":[3.069532634],"iteration":983,"passed_time":0.606198013,"remaining_time":0.009856878261},
{"learn":[3.068870784],"iteration":984,"passed_time":0.6067227387,"remaining_time":0.009239432568},
{"learn":[3.068801463],"iteration":985,"passed_time":0.6072644358,"remaining_time":0.008622415924},
{"learn":[3.067433249],"iteration":986,"passed_time":0.6078411785,"remaining_time":0.008006013497},
{"learn":[3.065611456],"iteration":987,"passed_time":0.6084096332,"remaining_time":0.007389590686},
{"learn":[3.063039162],"iteration":988,"passed_time":0.6089515737,"remaining_time":0.006772969981},
{"learn":[3.06177873],"iteration":989,"passed_time":0.6095015838,"remaining_time":0.006156581655},
{"learn":[3.061689148],"iteration":990,"passed_time":0.6100499434,"remaining_time":0.005540312301},
{"learn":[3.058984039],"iteration":991,"passed_time":0.6106574317,"remaining_time":0.004924656707},
{"learn":[3.057492984],"iteration":992,"passed_time":0.6112136182,"remaining_time":0.004308655919},
{"learn":[3.057290731],"iteration":993,"passed_time":0.6117509549,"remaining_time":0.0036926617},
{"learn":[3.056068348],"iteration":994,"passed_time":0.6123081502,"remaining_time":0.003076925378},
{"learn":[3.054987307],"iteration":995,"passed_time":0.6127948585,"remaining_time":0.002461023528},
{"learn":[3.054200234],"iteration":996,"passed_time":0.6133488939,"remaining_time":0.001845583432},
{"learn":[3.052732869],"iteration":997,"passed_time":0.6140013734,"remaining_time":0.001230463674},
{"learn":[3.051787862],"iteration":998,"passed_time":0.6144605432,"remaining_time":0.0006150756188},
{"learn":[3.051366222],"iteration":999,"passed_time":0.6149398456,"remaining_time":0}
]}